{"source":{"sourceId":"D","gurmukhi":"dsm bwxI","unicode":"ਦਸਮ ਬਾਣੀ","english":"Dasam Bani","pageNo":103},"count":72,"navigation":{"previous":102,"next":104},"page":[{"verseId":79067,"shabadId":7681,"verse":{"gurmukhi":"mDuBwr CMd ]","unicode":"ਮਧੁਭਾਰ ਛੰਦ ॥"},"larivaar":{"gurmukhi":"mDuBwrCMd]","unicode":"ਮਧੁਭਾਰਛੰਦ॥"},"translation":{"en":{"bdb":"MADHUBHAAR STANZA"},"pu":{"ss":{"gurmukhi":"mDuBwr CMd:","unicode":"ਮਧੁਭਾਰ ਛੰਦ:"},"ft":{"gurmukhi":"","unicode":""},"bdb":{"gurmukhi":"mDuBwr CMd:","unicode":"ਮਧੁਭਾਰ ਛੰਦ:"}},"es":{"sn":""},"hi":{}},"transliteration":{"english":"madhubhaar chha(n)dh ||","hindi":"मधुभार छंद ॥","en":"madhubhaar chha(n)dh ||","hi":"मधुभार छंद ॥","ipa":"mət̪ʊɓɑr ɕəŋd̪.","ur":"مدھبھار چھںد ۔۔"},"pageNo":103,"lineNo":79067,"updated":"2022-12-24 02:22:37","visraam":{"sttm":[],"igurbani":[],"sttm2":[]},"writer":{"writerId":47,"gurmukhi":"gurU goibMd isMG jI","unicode":null,"english":"Guru Gobind Singh Ji"},"raag":{"raagId":52,"gurmukhi":null,"unicode":null,"english":null,"raagWithPage":null}},{"verseId":79068,"shabadId":7681,"verse":{"gurmukhi":"muiK bmq juAwl ]","unicode":"ਮੁਖਿ ਬਮਤ ਜੁਆਲ ॥"},"larivaar":{"gurmukhi":"muiKbmqjuAwl]","unicode":"ਮੁਖਿਬਮਤਜੁਆਲ॥"},"translation":{"en":{"bdb":""},"pu":{"ss":{"gurmukhi":"(kwlkw) dy mUMh ivcoN AgnI inkl rhI sI।","unicode":"(ਕਾਲਕਾ) ਦੇ ਮੂੰਹ ਵਿਚੋਂ ਅਗਨੀ ਨਿਕਲ ਰਹੀ ਸੀ।"},"ft":{"gurmukhi":"","unicode":""},"bdb":{"gurmukhi":"(kwlkw) dy mUMh ivcoN AgnI inkl rhI sI।","unicode":"(ਕਾਲਕਾ) ਦੇ ਮੂੰਹ ਵਿਚੋਂ ਅਗਨੀ ਨਿਕਲ ਰਹੀ ਸੀ।"}},"es":{"sn":""},"hi":{}},"transliteration":{"english":"mukh bamat juaal ||","hindi":"मुखि बमत जुआल ॥","en":"mukh bamat juaal ||","hi":"मुखि बमत जुआल ॥","ipa":"mʊkʰ bəmət̪ d͡ʒʊəɑl.","ur":"مُکھ بمت جُآل ۔۔"},"pageNo":103,"lineNo":79068,"updated":"2022-12-24 02:22:37","visraam":{"sttm2":[],"sttm":[],"igurbani":[]},"writer":{"writerId":47,"gurmukhi":"gurU goibMd isMG jI","unicode":null,"english":"Guru Gobind Singh Ji"},"raag":{"raagId":52,"gurmukhi":null,"unicode":null,"english":null,"raagWithPage":null}},{"verseId":79069,"shabadId":7681,"verse":{"gurmukhi":"inksI kpwil ]","unicode":"ਨਿਕਸੀ ਕਪਾਲਿ ॥"},"larivaar":{"gurmukhi":"inksIkpwil]","unicode":"ਨਿਕਸੀਕਪਾਲਿ॥"},"translation":{"en":{"bdb":"The flames of fire come from her mouth and she herself came out from the forehead (of Durga)."},"pu":{"ss":{"gurmukhi":"(dyvI durgw dy) m`Qy qoN inklI","unicode":"(ਦੇਵੀ ਦੁਰਗਾ ਦੇ) ਮੱਥੇ ਤੋਂ ਨਿਕਲੀ"},"ft":{"gurmukhi":"","unicode":""},"bdb":{"gurmukhi":"(dyvI durgw dy) m`Qy qoN inklI","unicode":"(ਦੇਵੀ ਦੁਰਗਾ ਦੇ) ਮੱਥੇ ਤੋਂ ਨਿਕਲੀ"}},"es":{"sn":""},"hi":{}},"transliteration":{"english":"nikasee kapaal ||","hindi":"निकसी कपालि ॥","en":"nikasee kapaal ||","hi":"निकसी कपालि ॥","ipa":"nɪkəsi kəpɑl.","ur":"نِکسیِ کپال ۔۔"},"pageNo":103,"lineNo":79069,"updated":"2022-12-24 02:22:37","visraam":{"sttm2":[],"sttm":[],"igurbani":[]},"writer":{"writerId":47,"gurmukhi":"gurU goibMd isMG jI","unicode":null,"english":"Guru Gobind Singh Ji"},"raag":{"raagId":52,"gurmukhi":null,"unicode":null,"english":null,"raagWithPage":null}},{"verseId":79070,"shabadId":7681,"verse":{"gurmukhi":"mwry gjys ]","unicode":"ਮਾਰੇ ਗਜੇਸ ॥"},"larivaar":{"gurmukhi":"mwrygjys]","unicode":"ਮਾਰੇਗਜੇਸ॥"},"translation":{"en":{"bdb":""},"pu":{"ss":{"gurmukhi":"(aus ny) hwQIAW dy svwrw nUM mwr id`qw","unicode":"(ਉਸ ਨੇ) ਹਾਥੀਆਂ ਦੇ ਸਵਾਰਾ ਨੂੰ ਮਾਰ ਦਿੱਤਾ"},"ft":{"gurmukhi":"","unicode":""},"bdb":{"gurmukhi":"(aus ny) hwQIAW dy svwrw nUM mwr id`qw","unicode":"(ਉਸ ਨੇ) ਹਾਥੀਆਂ ਦੇ ਸਵਾਰਾ ਨੂੰ ਮਾਰ ਦਿੱਤਾ"}},"es":{"sn":""},"hi":{}},"transliteration":{"english":"maare gajes ||","hindi":"मारे गजेस ॥","en":"maare gajes ||","hi":"मारे गजेस ॥","ipa":"mɑre Gəd͡ʒes.","ur":"مارے گجےس ۔۔"},"pageNo":103,"lineNo":79070,"updated":"2022-12-24 02:22:37","visraam":{"sttm2":[],"sttm":[],"igurbani":[]},"writer":{"writerId":47,"gurmukhi":"gurU goibMd isMG jI","unicode":null,"english":"Guru Gobind Singh Ji"},"raag":{"raagId":52,"gurmukhi":null,"unicode":null,"english":null,"raagWithPage":null}},{"verseId":79071,"shabadId":7681,"verse":{"gurmukhi":"Cuty hYeys ]28]","unicode":"ਛੁਟੇ ਹੈਏਸ ॥੨੮॥"},"larivaar":{"gurmukhi":"CutyhYeys]28]","unicode":"ਛੁਟੇਹੈਏਸ॥੨੮॥"},"translation":{"en":{"bdb":"She killed the great elephants and the warriors on horseback.28."},"pu":{"ss":{"gurmukhi":"Aqy GoiVAW dy suAwmIAW nUM (GoiVAW qoN) ivCoV id`qw (ArQwq mwr id`qw) ]28]","unicode":"ਅਤੇ ਘੋੜਿਆਂ ਦੇ ਸੁਆਮੀਆਂ ਨੂੰ (ਘੋੜਿਆਂ ਤੋਂ) ਵਿਛੋੜ ਦਿੱਤਾ (ਅਰਥਾਤ ਮਾਰ ਦਿੱਤਾ) ॥੨੮॥"},"ft":{"gurmukhi":"","unicode":""},"bdb":{"gurmukhi":"Aqy GoiVAW dy suAwmIAW nUM (GoiVAW qoN) ivCoV id`qw (ArQwq mwr id`qw) ]28]","unicode":"ਅਤੇ ਘੋੜਿਆਂ ਦੇ ਸੁਆਮੀਆਂ ਨੂੰ (ਘੋੜਿਆਂ ਤੋਂ) ਵਿਛੋੜ ਦਿੱਤਾ (ਅਰਥਾਤ ਮਾਰ ਦਿੱਤਾ) ॥੨੮॥"}},"es":{"sn":""},"hi":{}},"transliteration":{"english":"chhuTe haies ||28||","hindi":"छुटे हैएस ॥२८॥","en":"chhuTe haies ||28||","hi":"छुटे हैएस ॥२८॥","ipa":"ɕʊʈe hæees.2ə8.","ur":"چھُٹے هَےاےس ۔۔۲۸۔۔"},"pageNo":103,"lineNo":79071,"updated":"2022-12-24 02:22:37","visraam":{"sttm2":[],"sttm":[],"igurbani":[]},"writer":{"writerId":47,"gurmukhi":"gurU goibMd isMG jI","unicode":null,"english":"Guru Gobind Singh Ji"},"raag":{"raagId":52,"gurmukhi":null,"unicode":null,"english":null,"raagWithPage":null}},{"verseId":79072,"shabadId":7681,"verse":{"gurmukhi":"CutMq bwx ]","unicode":"ਛੁਟੰਤ ਬਾਣ ॥"},"larivaar":{"gurmukhi":"CutMqbwx]","unicode":"ਛੁਟੰਤਬਾਣ॥"},"translation":{"en":{"bdb":""},"pu":{"ss":{"gurmukhi":"(Xu`D ivc) bwx cl rhy sn,","unicode":"(ਯੁੱਧ ਵਿਚ) ਬਾਣ ਚਲ ਰਹੇ ਸਨ,"},"ft":{"gurmukhi":"","unicode":""},"bdb":{"gurmukhi":"(Xu`D ivc) bwx cl rhy sn,","unicode":"(ਯੁੱਧ ਵਿਚ) ਬਾਣ ਚਲ ਰਹੇ ਸਨ,"}},"es":{"sn":""},"hi":{}},"transliteration":{"english":"chhuTa(n)t baan ||","hindi":"छुटंत बाण ॥","en":"chhuTa(n)t baan ||","hi":"छुटंत बाण ॥","ipa":"ɕʊʈəŋt̪ bɑɳ.","ur":"چھُٹںت باݨ ۔۔"},"pageNo":103,"lineNo":79072,"updated":"2022-12-24 02:22:37","visraam":{"sttm2":[],"sttm":[],"igurbani":[]},"writer":{"writerId":47,"gurmukhi":"gurU goibMd isMG jI","unicode":null,"english":"Guru Gobind Singh Ji"},"raag":{"raagId":52,"gurmukhi":null,"unicode":null,"english":null,"raagWithPage":null}},{"verseId":79073,"shabadId":7681,"verse":{"gurmukhi":"Jmkq ikRpwx ]","unicode":"ਝਮਕਤ ਕ੍ਰਿਪਾਣ ॥"},"larivaar":{"gurmukhi":"JmkqikRpwx]","unicode":"ਝਮਕਤਕ੍ਰਿਪਾਣ॥"},"translation":{"en":{"bdb":"The arrows are being shot and the swords are glistening."},"pu":{"ss":{"gurmukhi":"qlvwrw cmk rhIAW hn।","unicode":"ਤਲਵਾਰਾ ਚਮਕ ਰਹੀਆਂ ਹਨ।"},"ft":{"gurmukhi":"","unicode":""},"bdb":{"gurmukhi":"qlvwrw cmk rhIAW hn।","unicode":"ਤਲਵਾਰਾ ਚਮਕ ਰਹੀਆਂ ਹਨ।"}},"es":{"sn":""},"hi":{}},"transliteration":{"english":"jhamakat kirapaan ||","hindi":"झमकत कृपाण ॥","en":"jhamakat kirapaan ||","hi":"झमकत कृपाण ॥","ipa":"ɖ͡ʐəməkət̪ kɪɹəpɑɳ.","ur":"جھمکت کرپاݨ ۔۔"},"pageNo":103,"lineNo":79073,"updated":"2022-12-24 02:22:37","visraam":{"sttm2":[],"sttm":[],"igurbani":[]},"writer":{"writerId":47,"gurmukhi":"gurU goibMd isMG jI","unicode":null,"english":"Guru Gobind Singh Ji"},"raag":{"raagId":52,"gurmukhi":null,"unicode":null,"english":null,"raagWithPage":null}},{"verseId":79074,"shabadId":7681,"verse":{"gurmukhi":"swgM pRhwr ]","unicode":"ਸਾਗੰ ਪ੍ਰਹਾਰ ॥"},"larivaar":{"gurmukhi":"swgMpRhwr]","unicode":"ਸਾਗੰਪ੍ਰਹਾਰ॥"},"translation":{"en":{"bdb":""},"pu":{"ss":{"gurmukhi":"briCAW dy vwr ho rhy sn,","unicode":"ਬਰਛਿਆਂ ਦੇ ਵਾਰ ਹੋ ਰਹੇ ਸਨ,"},"ft":{"gurmukhi":"","unicode":""},"bdb":{"gurmukhi":"briCAW dy vwr ho rhy sn,","unicode":"ਬਰਛਿਆਂ ਦੇ ਵਾਰ ਹੋ ਰਹੇ ਸਨ,"}},"es":{"sn":""},"hi":{}},"transliteration":{"english":"saaga(n) prahaar ||","hindi":"सागं प्रहार ॥","en":"saaga(n) prahaar ||","hi":"सागं प्रहार ॥","ipa":"sɑGəŋ pɹəhɑr.","ur":"ساگں پرهار ۔۔"},"pageNo":103,"lineNo":79074,"updated":"2022-12-24 02:22:37","visraam":{"sttm2":[],"sttm":[],"igurbani":[]},"writer":{"writerId":47,"gurmukhi":"gurU goibMd isMG jI","unicode":null,"english":"Guru Gobind Singh Ji"},"raag":{"raagId":52,"gurmukhi":null,"unicode":null,"english":null,"raagWithPage":null}},{"verseId":79075,"shabadId":7681,"verse":{"gurmukhi":"Kylq Dmwr ]29]","unicode":"ਖੇਲਤ ਧਮਾਰ ॥੨੯॥"},"larivaar":{"gurmukhi":"KylqDmwr]29]","unicode":"ਖੇਲਤਧਮਾਰ॥੨੯॥"},"translation":{"en":{"bdb":"The daggers are being struck and it appears that the festival of Holi is being celebrated.29."},"pu":{"ss":{"gurmukhi":"(mwno sUrmy) Dmwl (nwc) pw rhy hox ]29]","unicode":"(ਮਾਨੋ ਸੂਰਮੇ) ਧਮਾਲ (ਨਾਚ) ਪਾ ਰਹੇ ਹੋਣ ॥੨੯॥"},"ft":{"gurmukhi":"","unicode":""},"bdb":{"gurmukhi":"(mwno sUrmy) Dmwl (nwc) pw rhy hox ]29]","unicode":"(ਮਾਨੋ ਸੂਰਮੇ) ਧਮਾਲ (ਨਾਚ) ਪਾ ਰਹੇ ਹੋਣ ॥੨੯॥"}},"es":{"sn":""},"hi":{}},"transliteration":{"english":"khelat dhamaar ||29||","hindi":"खेलत धमार ॥२९॥","en":"khelat dhamaar ||29||","hi":"खेलत धमार ॥२९॥","ipa":"kʰelət̪ t̪əmɑr.2ə9.","ur":"کھےلت دھمار ۔۔۲۹۔۔"},"pageNo":103,"lineNo":79075,"updated":"2022-12-24 02:22:37","visraam":{"sttm2":[],"sttm":[],"igurbani":[]},"writer":{"writerId":47,"gurmukhi":"gurU goibMd isMG jI","unicode":null,"english":"Guru Gobind Singh Ji"},"raag":{"raagId":52,"gurmukhi":null,"unicode":null,"english":null,"raagWithPage":null}},{"verseId":79076,"shabadId":7681,"verse":{"gurmukhi":"bwhY insMg ]","unicode":"ਬਾਹੈ ਨਿਸੰਗ ॥"},"larivaar":{"gurmukhi":"bwhYinsMg]","unicode":"ਬਾਹੈਨਿਸੰਗ॥"},"translation":{"en":{"bdb":""},"pu":{"ss":{"gurmukhi":"(dYNq) insMg ho ky (SsqR) clw rhy sn।","unicode":"(ਦੈਂਤ) ਨਿਸੰਗ ਹੋ ਕੇ (ਸ਼ਸਤ੍ਰ) ਚਲਾ ਰਹੇ ਸਨ।"},"ft":{"gurmukhi":"","unicode":""},"bdb":{"gurmukhi":"(dYNq) insMg ho ky (SsqR) clw rhy sn।","unicode":"(ਦੈਂਤ) ਨਿਸੰਗ ਹੋ ਕੇ (ਸ਼ਸਤ੍ਰ) ਚਲਾ ਰਹੇ ਸਨ।"}},"es":{"sn":""},"hi":{}},"transliteration":{"english":"baahai nisa(n)g ||","hindi":"बाहै निसंग ॥","en":"baahai nisa(n)g ||","hi":"बाहै निसंग ॥","ipa":"bɑhæ nɪsəŋG.","ur":"باهَے نسںگ ۔۔"},"pageNo":103,"lineNo":79076,"updated":"2022-12-24 02:22:37","visraam":{"sttm2":[],"sttm":[],"igurbani":[]},"writer":{"writerId":47,"gurmukhi":"gurU goibMd isMG jI","unicode":null,"english":"Guru Gobind Singh Ji"},"raag":{"raagId":52,"gurmukhi":null,"unicode":null,"english":null,"raagWithPage":null}},{"verseId":79077,"shabadId":7681,"verse":{"gurmukhi":"au`Ty JVMg ]","unicode":"ਉੱਠੇ ਝੜੰਗ ॥"},"larivaar":{"gurmukhi":"au`TyJVMg]","unicode":"ਉੱਠੇਝੜੰਗ॥"},"translation":{"en":{"bdb":"The weapons are being use unhesitatingly, which create clattering sounds."},"pu":{"ss":{"gurmukhi":"(aunHw dy vjx nwl) PulJVIAW pRgt huMdIAW sn।","unicode":"(ਉਨ੍ਹਾ ਦੇ ਵਜਣ ਨਾਲ) ਫੁਲਝੜੀਆਂ ਪ੍ਰਗਟ ਹੁੰਦੀਆਂ ਸਨ।"},"ft":{"gurmukhi":"","unicode":""},"bdb":{"gurmukhi":"(aunHw dy vjx nwl) PulJVIAW pRgt huMdIAW sn।","unicode":"(ਉਨ੍ਹਾ ਦੇ ਵਜਣ ਨਾਲ) ਫੁਲਝੜੀਆਂ ਪ੍ਰਗਟ ਹੁੰਦੀਆਂ ਸਨ।"}},"es":{"sn":""},"hi":{}},"transliteration":{"english":"au'The jhaRa(n)g ||","hindi":"उट्ठे झड़ंग ॥","en":"au'The jhaRa(n)g ||","hi":"उट्ठे झड़ंग ॥","ipa":"oʊʈʰe ɖ͡ʐəɽəŋG.","ur":"اُّٹھے جھڑںگ ۔۔"},"pageNo":103,"lineNo":79077,"updated":"2022-12-24 02:22:37","visraam":{"sttm2":[],"sttm":[],"igurbani":[]},"writer":{"writerId":47,"gurmukhi":"gurU goibMd isMG jI","unicode":null,"english":"Guru Gobind Singh Ji"},"raag":{"raagId":52,"gurmukhi":null,"unicode":null,"english":null,"raagWithPage":null}},{"verseId":79078,"shabadId":7681,"verse":{"gurmukhi":"qupk qVwk ]","unicode":"ਤੁਪਕ ਤੜਾਕ ॥"},"larivaar":{"gurmukhi":"qupkqVwk]","unicode":"ਤੁਪਕਤੜਾਕ॥"},"translation":{"en":{"bdb":""},"pu":{"ss":{"gurmukhi":"bMdUkw qoN qV-qV dI (Awvwz) ilkl rhI sI","unicode":"ਬੰਦੂਕਾ ਤੋਂ ਤੜ-ਤੜ ਦੀ (ਆਵਾਜ਼) ਲਿਕਲ ਰਹੀ ਸੀ"},"ft":{"gurmukhi":"","unicode":""},"bdb":{"gurmukhi":"bMdUkw qoN qV-qV dI (Awvwz) ilkl rhI sI","unicode":"ਬੰਦੂਕਾ ਤੋਂ ਤੜ-ਤੜ ਦੀ (ਆਵਾਜ਼) ਲਿਕਲ ਰਹੀ ਸੀ"}},"es":{"sn":""},"hi":{}},"transliteration":{"english":"tupak taRaak ||","hindi":"तुपक तड़ाक ॥","en":"tupak taRaak ||","hi":"तुपक तड़ाक ॥","ipa":"t̪ʊpək t̪əɽɑk.","ur":"تُپک تڑاک ۔۔"},"pageNo":103,"lineNo":79078,"updated":"2022-12-24 02:22:37","visraam":{"sttm2":[],"sttm":[],"igurbani":[]},"writer":{"writerId":47,"gurmukhi":"gurU goibMd isMG jI","unicode":null,"english":"Guru Gobind Singh Ji"},"raag":{"raagId":52,"gurmukhi":null,"unicode":null,"english":null,"raagWithPage":null}},{"verseId":79079,"shabadId":7681,"verse":{"gurmukhi":"auTq kVwk ]30]","unicode":"ਉਠਤ ਕੜਾਕ ॥੩੦॥"},"larivaar":{"gurmukhi":"auTqkVwk]30]","unicode":"ਉਠਤਕੜਾਕ॥੩੦॥"},"translation":{"en":{"bdb":"The guns boom and produce roaring sounds. 30"},"pu":{"ss":{"gurmukhi":"Aqy (golIAW vrHn nwl) kwV-kwV (dI Dun) auT rhI hY ]30]","unicode":"ਅਤੇ (ਗੋਲੀਆਂ ਵਰ੍ਹਨ ਨਾਲ) ਕਾੜ-ਕਾੜ (ਦੀ ਧੁਨ) ਉਠ ਰਹੀ ਹੈ ॥੩੦॥"},"ft":{"gurmukhi":"","unicode":""},"bdb":{"gurmukhi":"Aqy (golIAW vrHn nwl) kwV-kwV (dI Dun) auT rhI hY ]30]","unicode":"ਅਤੇ (ਗੋਲੀਆਂ ਵਰ੍ਹਨ ਨਾਲ) ਕਾੜ-ਕਾੜ (ਦੀ ਧੁਨ) ਉਠ ਰਹੀ ਹੈ ॥੩੦॥"}},"es":{"sn":""},"hi":{}},"transliteration":{"english":"auThat kaRaak ||30||","hindi":"उठत कड़ाक ॥३०॥","en":"auThat kaRaak ||30||","hi":"उठत कड़ाक ॥३०॥","ipa":"oʊʈʰət̪ kəɽɑk.3ə0.","ur":"اُٹھت کڑاک ۔۔۳۰۔۔"},"pageNo":103,"lineNo":79079,"updated":"2022-12-24 02:22:37","visraam":{"sttm2":[],"sttm":[],"igurbani":[]},"writer":{"writerId":47,"gurmukhi":"gurU goibMd isMG jI","unicode":null,"english":"Guru Gobind Singh Ji"},"raag":{"raagId":52,"gurmukhi":null,"unicode":null,"english":null,"raagWithPage":null}},{"verseId":79080,"shabadId":7681,"verse":{"gurmukhi":"brkMq mwie ]","unicode":"ਬਰਕੰਤ ਮਾਇ ॥"},"larivaar":{"gurmukhi":"brkMqmwie]","unicode":"ਬਰਕੰਤਮਾਇ॥"},"translation":{"en":{"bdb":""},"pu":{"ss":{"gurmukhi":"dyvI mwqw llkwrdI sI,","unicode":"ਦੇਵੀ ਮਾਤਾ ਲਲਕਾਰਦੀ ਸੀ,"},"ft":{"gurmukhi":"","unicode":""},"bdb":{"gurmukhi":"dyvI mwqw llkwrdI sI,","unicode":"ਦੇਵੀ ਮਾਤਾ ਲਲਕਾਰਦੀ ਸੀ,"}},"es":{"sn":""},"hi":{}},"transliteration":{"english":"baraka(n)t mai ||","hindi":"बरकंत माइ ॥","en":"baraka(n)t mai ||","hi":"बरकंत माइ ॥","ipa":"bərəkəŋt̪ mɑeɪ.","ur":"برکںت ماا ۔۔"},"pageNo":103,"lineNo":79080,"updated":"2022-12-24 02:22:37","visraam":{"sttm2":[],"sttm":[],"igurbani":[]},"writer":{"writerId":47,"gurmukhi":"gurU goibMd isMG jI","unicode":null,"english":"Guru Gobind Singh Ji"},"raag":{"raagId":52,"gurmukhi":null,"unicode":null,"english":null,"raagWithPage":null}},{"verseId":79081,"shabadId":7681,"verse":{"gurmukhi":"BBkMq Gwie ]","unicode":"ਭਭਕੰਤ ਘਾਇ ॥"},"larivaar":{"gurmukhi":"BBkMqGwie]","unicode":"ਭਭਕੰਤਘਾਇ॥"},"translation":{"en":{"bdb":"The Mother (goddess) challenges and the wounds bust."},"pu":{"ss":{"gurmukhi":"zKmw (ivcoN lhU) bG-bG kr ky inkl irhw sI।","unicode":"ਜ਼ਖਮਾ (ਵਿਚੋਂ ਲਹੂ) ਬਘ-ਬਘ ਕਰ ਕੇ ਨਿਕਲ ਰਿਹਾ ਸੀ।"},"ft":{"gurmukhi":"","unicode":""},"bdb":{"gurmukhi":"zKmw (ivcoN lhU) bG-bG kr ky inkl irhw sI।","unicode":"ਜ਼ਖਮਾ (ਵਿਚੋਂ ਲਹੂ) ਬਘ-ਬਘ ਕਰ ਕੇ ਨਿਕਲ ਰਿਹਾ ਸੀ।"}},"es":{"sn":""},"hi":{}},"transliteration":{"english":"bhabhaka(n)t ghai ||","hindi":"भभकंत घाइ ॥","en":"bhabhaka(n)t ghai ||","hi":"भभकंत घाइ ॥","ipa":"ɓəɓəkəŋt̪ Gʰɑeɪ.","ur":"بھبھکںت گھاا ۔۔"},"pageNo":103,"lineNo":79081,"updated":"2022-12-24 02:22:37","visraam":{"sttm2":[],"sttm":[],"igurbani":[]},"writer":{"writerId":47,"gurmukhi":"gurU goibMd isMG jI","unicode":null,"english":"Guru Gobind Singh Ji"},"raag":{"raagId":52,"gurmukhi":null,"unicode":null,"english":null,"raagWithPage":null}},{"verseId":79082,"shabadId":7681,"verse":{"gurmukhi":"juJy juAwx ]","unicode":"ਜੁਝੇ ਜੁਆਣ ॥"},"larivaar":{"gurmukhi":"juJyjuAwx]","unicode":"ਜੁਝੇਜੁਆਣ॥"},"translation":{"en":{"bdb":""},"pu":{"ss":{"gurmukhi":"sUrmy lV rhy sn,","unicode":"ਸੂਰਮੇ ਲੜ ਰਹੇ ਸਨ,"},"ft":{"gurmukhi":"","unicode":""},"bdb":{"gurmukhi":"sUrmy lV rhy sn,","unicode":"ਸੂਰਮੇ ਲੜ ਰਹੇ ਸਨ,"}},"es":{"sn":""},"hi":{}},"transliteration":{"english":"jujhe juaan ||","hindi":"जुझे जुआण ॥","en":"jujhe juaan ||","hi":"जुझे जुआण ॥","ipa":"d͡ʒʊɖ͡ʐe d͡ʒʊəɑɳ.","ur":"جُجھے جُآݨ ۔۔"},"pageNo":103,"lineNo":79082,"updated":"2022-12-24 02:22:37","visraam":{"sttm2":[],"sttm":[],"igurbani":[]},"writer":{"writerId":47,"gurmukhi":"gurU goibMd isMG jI","unicode":null,"english":"Guru Gobind Singh Ji"},"raag":{"raagId":52,"gurmukhi":null,"unicode":null,"english":null,"raagWithPage":null}},{"verseId":79083,"shabadId":7681,"verse":{"gurmukhi":"ncy ikkwx ]31]","unicode":"ਨਚੇ ਕਿਕਾਣ ॥੩੧॥"},"larivaar":{"gurmukhi":"ncyikkwx]31]","unicode":"ਨਚੇਕਿਕਾਣ॥੩੧॥"},"translation":{"en":{"bdb":"The youthful warriors fight and the horses dance.31"},"pu":{"ss":{"gurmukhi":"GoVy nc rhy sn ]31]","unicode":"ਘੋੜੇ ਨਚ ਰਹੇ ਸਨ ॥੩੧॥"},"ft":{"gurmukhi":"","unicode":""},"bdb":{"gurmukhi":"GoVy nc rhy sn ]31]","unicode":"ਘੋੜੇ ਨਚ ਰਹੇ ਸਨ ॥੩੧॥"}},"es":{"sn":""},"hi":{}},"transliteration":{"english":"nache kikaan ||31||","hindi":"नचे किकाण ॥३१॥","en":"nache kikaan ||31||","hi":"नचे किकाण ॥३१॥","ipa":"nət͡ʃe kɪkɑɳ.3ə1.","ur":"نچے ککاݨ ۔۔۳۱۔۔"},"pageNo":103,"lineNo":79083,"updated":"2022-12-24 02:22:37","visraam":{"sttm2":[],"sttm":[],"igurbani":[]},"writer":{"writerId":47,"gurmukhi":"gurU goibMd isMG jI","unicode":null,"english":"Guru Gobind Singh Ji"},"raag":{"raagId":52,"gurmukhi":null,"unicode":null,"english":null,"raagWithPage":null}},{"verseId":79084,"shabadId":7682,"verse":{"gurmukhi":"rUAwml CMd ]","unicode":"ਰੂਆਮਲ ਛੰਦ ॥"},"larivaar":{"gurmukhi":"rUAwmlCMd]","unicode":"ਰੂਆਮਲਛੰਦ॥"},"translation":{"en":{"bdb":"ROOAAL STANZA"},"pu":{"ss":{"gurmukhi":"rUAwml CMd:","unicode":"ਰੂਆਮਲ ਛੰਦ:"},"ft":{"gurmukhi":"","unicode":""},"bdb":{"gurmukhi":"rUAwml CMd:","unicode":"ਰੂਆਮਲ ਛੰਦ:"}},"es":{"sn":""},"hi":{}},"transliteration":{"english":"rooaamal chha(n)dh ||","hindi":"रूआमल छंद ॥","en":"rooaamal chha(n)dh ||","hi":"रूआमल छंद ॥","ipa":"ruəɑməl ɕəŋd̪.","ur":"رُوآمل چھںد ۔۔"},"pageNo":103,"lineNo":79084,"updated":"2022-12-24 02:22:37","visraam":{"sttm":[],"igurbani":[],"sttm2":[]},"writer":{"writerId":47,"gurmukhi":"gurU goibMd isMG jI","unicode":null,"english":"Guru Gobind Singh Ji"},"raag":{"raagId":52,"gurmukhi":null,"unicode":null,"english":null,"raagWithPage":null}},{"verseId":79085,"shabadId":7682,"verse":{"gurmukhi":"DweIXo AsuryWdR qih inj kop Ep bFwie ]","unicode":"ਧਾਈਯੋ ਅਸੁਰੇਾਂਦ੍ਰ ਤਹਿ ਨਿਜ ਕੋਪ ਓਪ ਬਢਾਇ ॥"},"larivaar":{"gurmukhi":"DweIXoAsuryWdRqihinjkopEpbFwie]","unicode":"ਧਾਈਯੋਅਸੁਰੇਾਂਦ੍ਰਤਹਿਨਿਜਕੋਪਓਪਬਢਾਇ॥"},"translation":{"en":{"bdb":"With increased anger, the demon-king sped forward."},"pu":{"ss":{"gurmukhi":"qdoN dYNq rwjw kRoiDq ho ky AwpxI SkqI nUM vDwauWdw hoieAw","unicode":"ਤਦੋਂ ਦੈਂਤ ਰਾਜਾ ਕ੍ਰੋਧਿਤ ਹੋ ਕੇ ਆਪਣੀ ਸ਼ਕਤੀ ਨੂੰ ਵਧਾਉਾਂਦਾ ਹੋਇਆ"},"ft":{"gurmukhi":"","unicode":""},"bdb":{"gurmukhi":"qdoN dYNq rwjw kRoiDq ho ky AwpxI SkqI nUM vDwauWdw hoieAw","unicode":"ਤਦੋਂ ਦੈਂਤ ਰਾਜਾ ਕ੍ਰੋਧਿਤ ਹੋ ਕੇ ਆਪਣੀ ਸ਼ਕਤੀ ਨੂੰ ਵਧਾਉਾਂਦਾ ਹੋਇਆ"}},"es":{"sn":""},"hi":{}},"transliteration":{"english":"dhaieeyo asureaa(n)dhr teh nij kop op baddai ||","hindi":"धाईयो असुरेाँद्र तहि निज कोप ओप बढाइ ॥","en":"dhaieeyo asureaa(n)dhr teh nij kop op baddai ||","hi":"धाईयो असुरेाँद्र तहि निज कोप ओप बढाइ ॥","ipa":"t̪ɑeijɔ əsʊreɑⁿəd̪ɹ t̪əh nɪd͡ʒ kɔp oəp bəʈɑeɪ.","ur":"دھاایےو اسرےاںدر تهِ نج کوپ اوپ بڈھاا ۔۔"},"pageNo":103,"lineNo":79085,"updated":"2022-12-24 02:22:37","visraam":{"sttm2":[],"sttm":[],"igurbani":[]},"writer":{"writerId":47,"gurmukhi":"gurU goibMd isMG jI","unicode":null,"english":"Guru Gobind Singh Ji"},"raag":{"raagId":52,"gurmukhi":null,"unicode":null,"english":null,"raagWithPage":null}},{"verseId":79086,"shabadId":7682,"verse":{"gurmukhi":"sMg lY cqurMg sYnw suD ssqR ncwie ]","unicode":"ਸੰਗ ਲੈ ਚਤੁਰੰਗ ਸੈਨਾ ਸੁਧ ਸਸਤ੍ਰ ਨਚਾਇ ॥"},"larivaar":{"gurmukhi":"sMglYcqurMgsYnwsuDssqRncwie]","unicode":"ਸੰਗਲੈਚਤੁਰੰਗਸੈਨਾਸੁਧਸਸਤ੍ਰਨਚਾਇ॥"},"translation":{"en":{"bdb":"He had four kinds of forces with him, who cause the dance of sharp weapons."},"pu":{"ss":{"gurmukhi":"cqurMgxI sYnw nUM nwl lY ky (Agy viDAw ijs dy sYink) hiQAwrw nUM GuMmw rhy sn।","unicode":"ਚਤੁਰੰਗਣੀ ਸੈਨਾ ਨੂੰ ਨਾਲ ਲੈ ਕੇ (ਅਗੇ ਵਧਿਆ ਜਿਸ ਦੇ ਸੈਨਿਕ) ਹਥਿਆਰਾ ਨੂੰ ਘੁੰਮਾ ਰਹੇ ਸਨ।"},"ft":{"gurmukhi":"","unicode":""},"bdb":{"gurmukhi":"cqurMgxI sYnw nUM nwl lY ky (Agy viDAw ijs dy sYink) hiQAwrw nUM GuMmw rhy sn।","unicode":"ਚਤੁਰੰਗਣੀ ਸੈਨਾ ਨੂੰ ਨਾਲ ਲੈ ਕੇ (ਅਗੇ ਵਧਿਆ ਜਿਸ ਦੇ ਸੈਨਿਕ) ਹਥਿਆਰਾ ਨੂੰ ਘੁੰਮਾ ਰਹੇ ਸਨ।"}},"es":{"sn":""},"hi":{}},"transliteration":{"english":"sa(n)g lai chatura(n)g sainaa sudh sasatr nachai ||","hindi":"संग लै चतुरंग सैना सुध ससत्र नचाइ ॥","en":"sa(n)g lai chatura(n)g sainaa sudh sasatr nachai ||","hi":"संग लै चतुरंग सैना सुध ससत्र नचाइ ॥","ipa":"səŋG læ t͡ʃət̪ʊrəŋG sænɑ sʊt̪ə̀ səsət̪ɹ nət͡ʃɑeɪ.","ur":"سںگ لَے چترںگ سَےنا سُدھ سستر نچاا ۔۔"},"pageNo":103,"lineNo":79086,"updated":"2022-12-24 02:22:37","visraam":{"sttm2":[],"sttm":[],"igurbani":[]},"writer":{"writerId":47,"gurmukhi":"gurU goibMd isMG jI","unicode":null,"english":"Guru Gobind Singh Ji"},"raag":{"raagId":52,"gurmukhi":null,"unicode":null,"english":null,"raagWithPage":null}},{"verseId":79087,"shabadId":7682,"verse":{"gurmukhi":"dyib ssqR lgY igrY rix ruiJ juiJ juAwx ]","unicode":"ਦੇਬਿ ਸਸਤ੍ਰ ਲਗੈ ਗਿਰੈ ਰਣਿ ਰੁਝਿ ਜੁਝਿ ਜੁਆਣ ॥"},"larivaar":{"gurmukhi":"dyibssqRlgYigrYrixruiJjuiJjuAwx]","unicode":"ਦੇਬਿਸਸਤ੍ਰਲਗੈਗਿਰੈਰਣਿਰੁਝਿਜੁਝਿਜੁਆਣ॥"},"translation":{"en":{"bdb":"Whosoever was struck by the weapons of the goddess, those fighting warriors fell in the field."},"pu":{"ss":{"gurmukhi":"(auh sYink) dyvI dy SsqR lgx nwl rx ivc jUJdy hoey ifg pey sn।","unicode":"(ਉਹ ਸੈਨਿਕ) ਦੇਵੀ ਦੇ ਸ਼ਸਤ੍ਰ ਲਗਣ ਨਾਲ ਰਣ ਵਿਚ ਜੂਝਦੇ ਹੋਏ ਡਿਗ ਪਏ ਸਨ।"},"ft":{"gurmukhi":"","unicode":""},"bdb":{"gurmukhi":"(auh sYink) dyvI dy SsqR lgx nwl rx ivc jUJdy hoey ifg pey sn।","unicode":"(ਉਹ ਸੈਨਿਕ) ਦੇਵੀ ਦੇ ਸ਼ਸਤ੍ਰ ਲਗਣ ਨਾਲ ਰਣ ਵਿਚ ਜੂਝਦੇ ਹੋਏ ਡਿਗ ਪਏ ਸਨ।"}},"es":{"sn":""},"hi":{}},"transliteration":{"english":"dheb sasatr lagai girai ran rujh jujh juaan ||","hindi":"देबि ससत्र लगै गिरै रणि रुझि जुझि जुआण ॥","en":"dheb sasatr lagai girai ran rujh jujh juaan ||","hi":"देबि ससत्र लगै गिरै रणि रुझि जुझि जुआण ॥","ipa":"d̪eb səsət̪ɹ ləGæ Gɪræ rəɳ rʊɖ͡ʐ d͡ʒʊɖ͡ʐ d͡ʒʊəɑɳ.","ur":"دےب سستر لگَے گرَے رݨ رُجھ جُجھ جُآݨ ۔۔"},"pageNo":103,"lineNo":79087,"updated":"2022-12-24 02:22:37","visraam":{"sttm2":[],"sttm":[],"igurbani":[]},"writer":{"writerId":47,"gurmukhi":"gurU goibMd isMG jI","unicode":null,"english":"Guru Gobind Singh Ji"},"raag":{"raagId":52,"gurmukhi":null,"unicode":null,"english":null,"raagWithPage":null}},{"verseId":79088,"shabadId":7682,"verse":{"gurmukhi":"pIlrwj iPry khUM rx suC CuC ikkwx ]32]","unicode":"ਪੀਲਰਾਜ ਫਿਰੇ ਕਹੂੰ ਰਣ ਸੁਛ ਛੁਛ ਕਿਕਾਣ ॥੩੨॥"},"larivaar":{"gurmukhi":"pIlrwjiPrykhUMrxsuCCuCikkwx]32]","unicode":"ਪੀਲਰਾਜਫਿਰੇਕਹੂੰਰਣਸੁਛਛੁਛਕਿਕਾਣ॥੩੨॥"},"translation":{"en":{"bdb":"Somewhere the elephants and somewhere horses are roaming without riders in the battlefield.32."},"pu":{"ss":{"gurmukhi":"rx ivc ikqy gj-rwj Aqy ikqy suMdr GoVy (svwrw qoN) ivCuMny (CUC) iPr rhy sn ]32]","unicode":"ਰਣ ਵਿਚ ਕਿਤੇ ਗਜ-ਰਾਜ ਅਤੇ ਕਿਤੇ ਸੁੰਦਰ ਘੋੜੇ (ਸਵਾਰਾ ਤੋਂ) ਵਿਛੁੰਨੇ (ਛੂਛ) ਫਿਰ ਰਹੇ ਸਨ ॥੩੨॥"},"ft":{"gurmukhi":"","unicode":""},"bdb":{"gurmukhi":"rx ivc ikqy gj-rwj Aqy ikqy suMdr GoVy (svwrw qoN) ivCuMny (CUC) iPr rhy sn ]32]","unicode":"ਰਣ ਵਿਚ ਕਿਤੇ ਗਜ-ਰਾਜ ਅਤੇ ਕਿਤੇ ਸੁੰਦਰ ਘੋੜੇ (ਸਵਾਰਾ ਤੋਂ) ਵਿਛੁੰਨੇ (ਛੂਛ) ਫਿਰ ਰਹੇ ਸਨ ॥੩੨॥"}},"es":{"sn":""},"hi":{}},"transliteration":{"english":"peelaraaj fire kahoo(n) ran suchh chhuchh kikaan ||32||","hindi":"पीलराज फिरे कहूँ रण सुछ छुछ किकाण ॥३२॥","en":"peelaraaj fire kahoo(n) ran suchh chhuchh kikaan ||32||","hi":"पीलराज फिरे कहूँ रण सुछ छुछ किकाण ॥३२॥","ipa":"pilərɑd͡ʒ fɪre kəhuŋ rəɳ sʊɕ ɕʊɕ kɪkɑɳ.3ə2.","ur":"پیِلراج پھرے کهُوں رݨ سُچھ چھُچھ ککاݨ ۔۔۳۲۔۔"},"pageNo":103,"lineNo":79088,"updated":"2022-12-24 02:22:37","visraam":{"sttm2":[],"sttm":[],"igurbani":[]},"writer":{"writerId":47,"gurmukhi":"gurU goibMd isMG jI","unicode":null,"english":"Guru Gobind Singh Ji"},"raag":{"raagId":52,"gurmukhi":null,"unicode":null,"english":null,"raagWithPage":null}},{"verseId":79089,"shabadId":7682,"verse":{"gurmukhi":"cIr cwmr puMj kuMjr bwj rwj Anyk ]","unicode":"ਚੀਰ ਚਾਮਰ ਪੁੰਜ ਕੁੰਜਰ ਬਾਜ ਰਾਜ ਅਨੇਕ ॥"},"larivaar":{"gurmukhi":"cIrcwmrpuMjkuMjrbwjrwjAnyk]","unicode":"ਚੀਰਚਾਮਰਪੁੰਜਕੁੰਜਰਬਾਜਰਾਜਅਨੇਕ॥"},"translation":{"en":{"bdb":"Somewhere clothes, turbans and fly-whisks are lying scattered and somewhere elephants, horses and chieftains are lying dead."},"pu":{"ss":{"gurmukhi":"(Xu`D-BUmI ivc ikqy) bsqR, cOrw Aqy hwQIAW dy JuMf Aqy Anyk sRyST GoVy","unicode":"(ਯੁੱਧ-ਭੂਮੀ ਵਿਚ ਕਿਤੇ) ਬਸਤ੍ਰ, ਚੌਰਾ ਅਤੇ ਹਾਥੀਆਂ ਦੇ ਝੁੰਡ ਅਤੇ ਅਨੇਕ ਸ੍ਰੇਸ਼ਠ ਘੋੜੇ"},"ft":{"gurmukhi":"","unicode":""},"bdb":{"gurmukhi":"(Xu`D-BUmI ivc ikqy) bsqR, cOrw Aqy hwQIAW dy JuMf Aqy Anyk sRyST GoVy","unicode":"(ਯੁੱਧ-ਭੂਮੀ ਵਿਚ ਕਿਤੇ) ਬਸਤ੍ਰ, ਚੌਰਾ ਅਤੇ ਹਾਥੀਆਂ ਦੇ ਝੁੰਡ ਅਤੇ ਅਨੇਕ ਸ੍ਰੇਸ਼ਠ ਘੋੜੇ"}},"es":{"sn":""},"hi":{}},"transliteration":{"english":"cheer chaamar pu(n)j ku(n)jar baaj raaj anek ||","hindi":"चीर चामर पुँज कुँजर बाज राज अनेक ॥","en":"cheer chaamar pu(n)j ku(n)jar baaj raaj anek ||","hi":"चीर चामर पुँज कुँजर बाज राज अनेक ॥","ipa":"t͡ʃir t͡ʃɑmər pʊŋd͡ʒ kʊŋd͡ʒər bɑd͡ʒ rɑd͡ʒ ənek.","ur":"چیِر چامر پُںج کُںجر باج راج انےک ۔۔"},"pageNo":103,"lineNo":79089,"updated":"2022-12-24 02:22:37","visraam":{"sttm":[],"igurbani":[],"sttm2":[]},"writer":{"writerId":47,"gurmukhi":"gurU goibMd isMG jI","unicode":null,"english":"Guru Gobind Singh Ji"},"raag":{"raagId":52,"gurmukhi":null,"unicode":null,"english":null,"raagWithPage":null}},{"verseId":79090,"shabadId":7682,"verse":{"gurmukhi":"ssqR AsqR suBy khUM srdwr suAwr Anyk ]","unicode":"ਸਸਤ੍ਰ ਅਸਤ੍ਰ ਸੁਭੇ ਕਹੂੰ ਸਰਦਾਰ ਸੁਆਰ ਅਨੇਕ ॥"},"larivaar":{"gurmukhi":"ssqRAsqRsuBykhUMsrdwrsuAwrAnyk]","unicode":"ਸਸਤ੍ਰਅਸਤ੍ਰਸੁਭੇਕਹੂੰਸਰਦਾਰਸੁਆਰਅਨੇਕ॥"},"translation":{"en":{"bdb":"Somewhere generals and warriors with weapons and aromuts are lying down."},"pu":{"ss":{"gurmukhi":"Aqy ikqy AsqR-SsqRw nwl sjy srdwr Aqy svwr (ifgy pey sn)","unicode":"ਅਤੇ ਕਿਤੇ ਅਸਤ੍ਰ-ਸ਼ਸਤ੍ਰਾ ਨਾਲ ਸਜੇ ਸਰਦਾਰ ਅਤੇ ਸਵਾਰ (ਡਿਗੇ ਪਏ ਸਨ)"},"ft":{"gurmukhi":"","unicode":""},"bdb":{"gurmukhi":"Aqy ikqy AsqR-SsqRw nwl sjy srdwr Aqy svwr (ifgy pey sn)","unicode":"ਅਤੇ ਕਿਤੇ ਅਸਤ੍ਰ-ਸ਼ਸਤ੍ਰਾ ਨਾਲ ਸਜੇ ਸਰਦਾਰ ਅਤੇ ਸਵਾਰ (ਡਿਗੇ ਪਏ ਸਨ)"}},"es":{"sn":""},"hi":{}},"transliteration":{"english":"sasatr asatr subhe kahoo(n) saradhaar suaar anek ||","hindi":"ससत्र असत्र सुभे कहूँ सरदार सुआर अनेक ॥","en":"sasatr asatr subhe kahoo(n) saradhaar suaar anek ||","hi":"ससत्र असत्र सुभे कहूँ सरदार सुआर अनेक ॥","ipa":"səsət̪ɹ əsət̪ɹ sʊɓe kəhuŋ sərəd̪ɑr sʊəɑr ənek.","ur":"سستر استر سُبھے کهُوں سردار سُآر انےک ۔۔"},"pageNo":103,"lineNo":79090,"updated":"2022-12-24 02:22:37","visraam":{"sttm":[],"igurbani":[],"sttm2":[]},"writer":{"writerId":47,"gurmukhi":"gurU goibMd isMG jI","unicode":null,"english":"Guru Gobind Singh Ji"},"raag":{"raagId":52,"gurmukhi":null,"unicode":null,"english":null,"raagWithPage":null}},{"verseId":79091,"shabadId":7682,"verse":{"gurmukhi":"qygu qIr quPMg qbr kuhuk bwn AnMq ]","unicode":"ਤੇਗੁ ਤੀਰ ਤੁਫੰਗ ਤਬਰ ਕੁਹੁਕ ਬਾਨ ਅਨੰਤ ॥"},"larivaar":{"gurmukhi":"qyguqIrquPMgqbrkuhukbwnAnMq]","unicode":"ਤੇਗੁਤੀਰਤੁਫੰਗਤਬਰਕੁਹੁਕਬਾਨਅਨੰਤ॥"},"translation":{"en":{"bdb":"Somewhere the sonund of arrows, swords, guns, axes and special shafts is being heard."},"pu":{"ss":{"gurmukhi":"(ikqy) qlvwrw, qIr, bMdUkw, kuhwVy, (sItI dI Awvwz kFx vwly) kuhuk bwx (iKMfy) pey sn","unicode":"(ਕਿਤੇ) ਤਲਵਾਰਾ, ਤੀਰ, ਬੰਦੂਕਾ, ਕੁਹਾੜੇ, (ਸੀਟੀ ਦੀ ਆਵਾਜ਼ ਕਢਣ ਵਾਲੇ) ਕੁਹੁਕ ਬਾਣ (ਖਿੰਡੇ) ਪਏ ਸਨ"},"ft":{"gurmukhi":"","unicode":""},"bdb":{"gurmukhi":"(ikqy) qlvwrw, qIr, bMdUkw, kuhwVy, (sItI dI Awvwz kFx vwly) kuhuk bwx (iKMfy) pey sn","unicode":"(ਕਿਤੇ) ਤਲਵਾਰਾ, ਤੀਰ, ਬੰਦੂਕਾ, ਕੁਹਾੜੇ, (ਸੀਟੀ ਦੀ ਆਵਾਜ਼ ਕਢਣ ਵਾਲੇ) ਕੁਹੁਕ ਬਾਣ (ਖਿੰਡੇ) ਪਏ ਸਨ"}},"es":{"sn":""},"hi":{}},"transliteration":{"english":"teg teer tufa(n)g tabar kuhuk baan ana(n)t ||","hindi":"तेगु तीर तुफंग तबर कुहुक बान अनंत ॥","en":"teg teer tufa(n)g tabar kuhuk baan ana(n)t ||","hi":"तेगु तीर तुफंग तबर कुहुक बान अनंत ॥","ipa":"t̪eG t̪ir t̪ʊfəŋG t̪əbər kʊhʊk bɑn ənəŋt̪.","ur":"تےگ تیِر تُپھںگ تبر کُهُک بان انںت ۔۔"},"pageNo":103,"lineNo":79091,"updated":"2022-12-24 02:22:37","visraam":{"sttm2":[],"sttm":[],"igurbani":[]},"writer":{"writerId":47,"gurmukhi":"gurU goibMd isMG jI","unicode":null,"english":"Guru Gobind Singh Ji"},"raag":{"raagId":52,"gurmukhi":null,"unicode":null,"english":null,"raagWithPage":null}},{"verseId":79092,"shabadId":7682,"verse":{"gurmukhi":"byiD byiD igrY briCn sUr soBwvMq ]33]","unicode":"ਬੇਧਿ ਬੇਧਿ ਗਿਰੈ ਬਰਛਿਨ ਸੂਰ ਸੋਭਾਵੰਤ ॥੩੩॥"},"larivaar":{"gurmukhi":"byiDbyiDigrYbriCnsUrsoBwvMq]33]","unicode":"ਬੇਧਿਬੇਧਿਗਿਰੈਬਰਛਿਨਸੂਰਸੋਭਾਵੰਤ॥੩੩॥"},"translation":{"en":{"bdb":"Somewhere the heroes pierced by the daggers have fallen gracefully.33."},"pu":{"ss":{"gurmukhi":"Aqy ikqy briCAW nwl ivMnHy hoey sUrbIr ifgy hoey SoBw pw rhy sn ]33]","unicode":"ਅਤੇ ਕਿਤੇ ਬਰਛਿਆਂ ਨਾਲ ਵਿੰਨ੍ਹੇ ਹੋਏ ਸੂਰਬੀਰ ਡਿਗੇ ਹੋਏ ਸ਼ੋਭਾ ਪਾ ਰਹੇ ਸਨ ॥੩੩॥"},"ft":{"gurmukhi":"","unicode":""},"bdb":{"gurmukhi":"Aqy ikqy briCAW nwl ivMnHy hoey sUrbIr ifgy hoey SoBw pw rhy sn ]33]","unicode":"ਅਤੇ ਕਿਤੇ ਬਰਛਿਆਂ ਨਾਲ ਵਿੰਨ੍ਹੇ ਹੋਏ ਸੂਰਬੀਰ ਡਿਗੇ ਹੋਏ ਸ਼ੋਭਾ ਪਾ ਰਹੇ ਸਨ ॥੩੩॥"}},"es":{"sn":""},"hi":{}},"transliteration":{"english":"bedh bedh girai barachhin soor sobhaava(n)t ||33||","hindi":"बेधि बेधि गिरै बरछिन सूर सोभावंत ॥३३॥","en":"bedh bedh girai barachhin soor sobhaava(n)t ||33||","hi":"बेधि बेधि गिरै बरछिन सूर सोभावंत ॥३३॥","ipa":"bet̪ə̀ bet̪ə̀ Gɪræ bərəɕɪn sur sɔɓɑʋəŋt̪.3ə3.","ur":"بےدھ بےدھ گرَے برچھن سُور سوبھاوںت ۔۔۳۳۔۔"},"pageNo":103,"lineNo":79092,"updated":"2022-12-24 02:22:37","visraam":{"sttm2":[],"sttm":[],"igurbani":[]},"writer":{"writerId":47,"gurmukhi":"gurU goibMd isMG jI","unicode":null,"english":"Guru Gobind Singh Ji"},"raag":{"raagId":52,"gurmukhi":null,"unicode":null,"english":null,"raagWithPage":null}},{"verseId":79093,"shabadId":7682,"verse":{"gurmukhi":"igRD ibRD aufy qhw iPkrMq suAwn isRMgwl ]","unicode":"ਗ੍ਰਿਧ ਬ੍ਰਿਧ ਉਡੇ ਤਹਾ ਫਿਕਰੰਤ ਸੁਆਨ ਸ੍ਰਿੰਗਾਲ ॥"},"larivaar":{"gurmukhi":"igRDibRDaufyqhwiPkrMqsuAwnisRMgwl]","unicode":"ਗ੍ਰਿਧਬ੍ਰਿਧਉਡੇਤਹਾਫਿਕਰੰਤਸੁਆਨਸ੍ਰਿੰਗਾਲ॥"},"translation":{"en":{"bdb":"Large-sized vultures are flying there, the dogs are barking and the jackals are howling."},"pu":{"ss":{"gurmukhi":"auQy (Xu`D-BUmI ivc) vfIAW vfIAW igDw auf rhIAW sn Aqy ku`qy qy igdV bol ('iPkrMq') rhy sn।","unicode":"ਉਥੇ (ਯੁੱਧ-ਭੂਮੀ ਵਿਚ) ਵਡੀਆਂ ਵਡੀਆਂ ਗਿਧਾ ਉਡ ਰਹੀਆਂ ਸਨ ਅਤੇ ਕੁੱਤੇ ਤੇ ਗਿਦੜ ਬੋਲ ('ਫਿਕਰੰਤ') ਰਹੇ ਸਨ।"},"ft":{"gurmukhi":"","unicode":""},"bdb":{"gurmukhi":"auQy (Xu`D-BUmI ivc) vfIAW vfIAW igDw auf rhIAW sn Aqy ku`qy qy igdV bol ('iPkrMq') rhy sn।","unicode":"ਉਥੇ (ਯੁੱਧ-ਭੂਮੀ ਵਿਚ) ਵਡੀਆਂ ਵਡੀਆਂ ਗਿਧਾ ਉਡ ਰਹੀਆਂ ਸਨ ਅਤੇ ਕੁੱਤੇ ਤੇ ਗਿਦੜ ਬੋਲ ('ਫਿਕਰੰਤ') ਰਹੇ ਸਨ।"}},"es":{"sn":""},"hi":{}},"transliteration":{"english":"giradh biradh udde tahaa fikara(n)t suaan sira(n)gaal ||","hindi":"गृध बृध उडे तहा फिकरंत सुआन सृंगाल ॥","en":"giradh biradh udde tahaa fikara(n)t suaan sira(n)gaal ||","hi":"गृध बृध उडे तहा फिकरंत सुआन सृंगाल ॥","ipa":"Gɪɹət̪ə̀ bɪɹət̪ə̀ oʊɖe t̪əhɑ fɪkərəŋt̪ sʊəɑn sɪɹəŋGɑl.","ur":"گِردھ بردھ اُڈے تها پھکرںت سُآن سرںگال ۔۔"},"pageNo":103,"lineNo":79093,"updated":"2022-12-24 02:22:37","visraam":{"sttm2":[],"sttm":[],"igurbani":[]},"writer":{"writerId":47,"gurmukhi":"gurU goibMd isMG jI","unicode":null,"english":"Guru Gobind Singh Ji"},"raag":{"raagId":52,"gurmukhi":null,"unicode":null,"english":null,"raagWithPage":null}},{"verseId":79094,"shabadId":7682,"verse":{"gurmukhi":"mq dMiq spC pbY kMk bMk rswl ]","unicode":"ਮਤ ਦੰਤਿ ਸਪਛ ਪਬੈ ਕੰਕ ਬੰਕ ਰਸਾਲ ॥"},"larivaar":{"gurmukhi":"mqdMiqspCpbYkMkbMkrswl]","unicode":"ਮਤਦੰਤਿਸਪਛਪਬੈਕੰਕਬੰਕਰਸਾਲ॥"},"translation":{"en":{"bdb":"The intoxicated elephants look like the winged mountains and the crows, flying down to eat the flesh."},"pu":{"ss":{"gurmukhi":"(ifgy hoey) msq hwQI p`Kw vwly prbqw (vrgy lgdy sn Aqy aunHw auqy bYTy) kw nokIlI dB ('rswl') (ijhy pRqIq huMdy sn)।","unicode":"(ਡਿਗੇ ਹੋਏ) ਮਸਤ ਹਾਥੀ ਪੱਖਾ ਵਾਲੇ ਪਰਬਤਾ (ਵਰਗੇ ਲਗਦੇ ਸਨ ਅਤੇ ਉਨ੍ਹਾ ਉਤੇ ਬੈਠੇ) ਕਾ ਨੋਕੀਲੀ ਦਭ ('ਰਸਾਲ') (ਜਿਹੇ ਪ੍ਰਤੀਤ ਹੁੰਦੇ ਸਨ)।"},"ft":{"gurmukhi":"","unicode":""},"bdb":{"gurmukhi":"(ifgy hoey) msq hwQI p`Kw vwly prbqw (vrgy lgdy sn Aqy aunHw auqy bYTy) kw nokIlI dB ('rswl') (ijhy pRqIq huMdy sn)।","unicode":"(ਡਿਗੇ ਹੋਏ) ਮਸਤ ਹਾਥੀ ਪੱਖਾ ਵਾਲੇ ਪਰਬਤਾ (ਵਰਗੇ ਲਗਦੇ ਸਨ ਅਤੇ ਉਨ੍ਹਾ ਉਤੇ ਬੈਠੇ) ਕਾ ਨੋਕੀਲੀ ਦਭ ('ਰਸਾਲ') (ਜਿਹੇ ਪ੍ਰਤੀਤ ਹੁੰਦੇ ਸਨ)।"}},"es":{"sn":""},"hi":{}},"transliteration":{"english":"mat dha(n)t sapachh pabai ka(n)k ba(n)k rasaal ||","hindi":"मत दंति सपछ पबै कंक बंक रसाल ॥","en":"mat dha(n)t sapachh pabai ka(n)k ba(n)k rasaal ||","hi":"मत दंति सपछ पबै कंक बंक रसाल ॥","ipa":"mət̪ d̪əŋt̪ səpəɕ pəbæ kəŋk bəŋk rəsɑl.","ur":"مت دںت سپچھ پبَے کںک بںک رسال ۔۔"},"pageNo":103,"lineNo":79094,"updated":"2022-12-24 02:22:37","visraam":{"sttm2":[],"sttm":[],"igurbani":[]},"writer":{"writerId":47,"gurmukhi":"gurU goibMd isMG jI","unicode":null,"english":"Guru Gobind Singh Ji"},"raag":{"raagId":52,"gurmukhi":null,"unicode":null,"english":null,"raagWithPage":null}},{"verseId":79095,"shabadId":7682,"verse":{"gurmukhi":"CudR mIn Curu`DRkw Aru crm kCp AnMq ]","unicode":"ਛੁਦ੍ਰ ਮੀਨ ਛੁਰੁੱਧ੍ਰਕਾ ਅਰੁ ਚਰਮ ਕਛਪ ਅਨੰਤ ॥"},"larivaar":{"gurmukhi":"CudRmInCuru`DRkwArucrmkCpAnMq]","unicode":"ਛੁਦ੍ਰਮੀਨਛੁਰੁੱਧ੍ਰਕਾਅਰੁਚਰਮਕਛਪਅਨੰਤ॥"},"translation":{"en":{"bdb":"Thhe swords on the bodies of the demons appear like small fish and the shields look like tortoises."},"pu":{"ss":{"gurmukhi":"CotIAW CurIAW in`kIAW m`CIAW ijhIAW sn Aqy AnMq Fwlw k`CUAW vwg sn।","unicode":"ਛੋਟੀਆਂ ਛੁਰੀਆਂ ਨਿੱਕੀਆਂ ਮੱਛੀਆਂ ਜਿਹੀਆਂ ਸਨ ਅਤੇ ਅਨੰਤ ਢਾਲਾ ਕੱਛੂਆਂ ਵਾਗ ਸਨ।"},"ft":{"gurmukhi":"","unicode":""},"bdb":{"gurmukhi":"CotIAW CurIAW in`kIAW m`CIAW ijhIAW sn Aqy AnMq Fwlw k`CUAW vwg sn।","unicode":"ਛੋਟੀਆਂ ਛੁਰੀਆਂ ਨਿੱਕੀਆਂ ਮੱਛੀਆਂ ਜਿਹੀਆਂ ਸਨ ਅਤੇ ਅਨੰਤ ਢਾਲਾ ਕੱਛੂਆਂ ਵਾਗ ਸਨ।"}},"es":{"sn":""},"hi":{}},"transliteration":{"english":"chhudhr meen chhuru'dhrakaa ar charam kachhap ana(n)t ||","hindi":"छुद्र मीन छुरुद्ध्रका अरु चरम कछप अनंत ॥","en":"chhudhr meen chhuru'dhrakaa ar charam kachhap ana(n)t ||","hi":"छुद्र मीन छुरुद्ध्रका अरु चरम कछप अनंत ॥","ipa":"ɕʊd̪ɹ min ɕʊrʊt̪ə̀ɹəkɑ ər t͡ʃərəm kəɕəp ənəŋt̪.","ur":"چھُدر میٍن چھُرّدھرکا ار چرم کچھپ انںت ۔۔"},"pageNo":103,"lineNo":79095,"updated":"2022-12-24 02:22:37","visraam":{"sttm2":[],"sttm":[],"igurbani":[]},"writer":{"writerId":47,"gurmukhi":"gurU goibMd isMG jI","unicode":null,"english":"Guru Gobind Singh Ji"},"raag":{"raagId":52,"gurmukhi":null,"unicode":null,"english":null,"raagWithPage":null}},{"verseId":79096,"shabadId":7682,"verse":{"gurmukhi":"nkR bkR su brm soiBq sRox nIr durMq ]34]","unicode":"ਨਕ੍ਰ ਬਕ੍ਰ ਸੁ ਬਰਮ ਸੋਭਿਤ ਸ੍ਰੋਣ ਨੀਰ ਦੁਰੰਤ ॥੩੪॥"},"larivaar":{"gurmukhi":"nkRbkRsubrmsoiBqsRoxnIrdurMq]34]","unicode":"ਨਕ੍ਰਬਕ੍ਰਸੁਬਰਮਸੋਭਿਤਸ੍ਰੋਣਨੀਰਦੁਰੰਤ॥੩੪॥"},"translation":{"en":{"bdb":"On their bodies, the steel-armour looks elegant and the blood is flowing down like flood.34."},"pu":{"ss":{"gurmukhi":"kvc ('brm') iBAwnk mgrm`C vrgy soB rhy sn Aqy lhU AQwh pwxI dI ndI dy smwn sI ]34]","unicode":"ਕਵਚ ('ਬਰਮ') ਭਿਆਨਕ ਮਗਰਮੱਛ ਵਰਗੇ ਸੋਭ ਰਹੇ ਸਨ ਅਤੇ ਲਹੂ ਅਥਾਹ ਪਾਣੀ ਦੀ ਨਦੀ ਦੇ ਸਮਾਨ ਸੀ ॥੩੪॥"},"ft":{"gurmukhi":"","unicode":""},"bdb":{"gurmukhi":"kvc ('brm') iBAwnk mgrm`C vrgy soB rhy sn Aqy lhU AQwh pwxI dI ndI dy smwn sI ]34]","unicode":"ਕਵਚ ('ਬਰਮ') ਭਿਆਨਕ ਮਗਰਮੱਛ ਵਰਗੇ ਸੋਭ ਰਹੇ ਸਨ ਅਤੇ ਲਹੂ ਅਥਾਹ ਪਾਣੀ ਦੀ ਨਦੀ ਦੇ ਸਮਾਨ ਸੀ ॥੩੪॥"}},"es":{"sn":""},"hi":{}},"transliteration":{"english":"nakr bakr su baram sobhit sron neer dhura(n)t ||34||","hindi":"नक्र बक्र सु बरम सोभित स्रोण नीर दुरंत ॥३४॥","en":"nakr bakr su baram sobhit sron neer dhura(n)t ||34||","hi":"नक्र बक्र सु बरम सोभित स्रोण नीर दुरंत ॥३४॥","ipa":"nəkɹ bəkɹ s bərəm sɔɓɪt̪ sɹɔɳ nir d̪ʊrəŋt̪.3ə4.","ur":"نکر بکر سُ برم سوبھت سروݨ نیِر دُرںت ۔۔۳۴۔۔"},"pageNo":103,"lineNo":79096,"updated":"2022-12-24 02:22:37","visraam":{"sttm2":[],"sttm":[],"igurbani":[]},"writer":{"writerId":47,"gurmukhi":"gurU goibMd isMG jI","unicode":null,"english":"Guru Gobind Singh Ji"},"raag":{"raagId":52,"gurmukhi":null,"unicode":null,"english":null,"raagWithPage":null}},{"verseId":79097,"shabadId":7682,"verse":{"gurmukhi":"nv sUr nvkw sy rQI AiqrQI jwnu jhwj ]","unicode":"ਨਵ ਸੂਰ ਨਵਕਾ ਸੇ ਰਥੀ ਅਤਿਰਥੀ ਜਾਨੁ ਜਹਾਜ ॥"},"larivaar":{"gurmukhi":"nvsUrnvkwsyrQIAiqrQIjwnujhwj]","unicode":"ਨਵਸੂਰਨਵਕਾਸੇਰਥੀਅਤਿਰਥੀਜਾਨੁਜਹਾਜ॥"},"translation":{"en":{"bdb":"The new young warriors appear like boats and thhe charioteers look like shimps."},"pu":{"ss":{"gurmukhi":"nvyW (nOjvwn) sUrmy byVIAW ijhy sn Aqy rQI-mhwrQI jhwz sn,","unicode":"ਨਵੇਾਂ (ਨੌਜਵਾਨ) ਸੂਰਮੇ ਬੇੜੀਆਂ ਜਿਹੇ ਸਨ ਅਤੇ ਰਥੀ-ਮਹਾਰਥੀ ਜਹਾਜ਼ ਸਨ,"},"ft":{"gurmukhi":"","unicode":""},"bdb":{"gurmukhi":"nvyW (nOjvwn) sUrmy byVIAW ijhy sn Aqy rQI-mhwrQI jhwz sn,","unicode":"ਨਵੇਾਂ (ਨੌਜਵਾਨ) ਸੂਰਮੇ ਬੇੜੀਆਂ ਜਿਹੇ ਸਨ ਅਤੇ ਰਥੀ-ਮਹਾਰਥੀ ਜਹਾਜ਼ ਸਨ,"}},"es":{"sn":""},"hi":{}},"transliteration":{"english":"nav soor navakaa se rathee atirathee jaan jahaaj ||","hindi":"नव सूर नवका से रथी अतिरथी जानु जहाज ॥","en":"nav soor navakaa se rathee atirathee jaan jahaaj ||","hi":"नव सूर नवका से रथी अतिरथी जानु जहाज ॥","ipa":"nəʋ sur nəʋəkɑ se rət̪ʰi ət̪ɪrət̪ʰi d͡ʒɑn d͡ʒəhɑd͡ʒ.","ur":"نو سُور نوکا سے رتھیِ اترتھیِ جان جهاج ۔۔"},"pageNo":103,"lineNo":79097,"updated":"2022-12-24 02:22:37","visraam":{"sttm2":[],"sttm":[],"igurbani":[]},"writer":{"writerId":47,"gurmukhi":"gurU goibMd isMG jI","unicode":null,"english":"Guru Gobind Singh Ji"},"raag":{"raagId":52,"gurmukhi":null,"unicode":null,"english":null,"raagWithPage":null}},{"verseId":79098,"shabadId":7682,"verse":{"gurmukhi":"lwid lwid mno cly Dn DIr bIr slwj ]","unicode":"ਲਾਦਿ ਲਾਦਿ ਮਨੋ ਚਲੇ ਧਨ ਧੀਰ ਬੀਰ ਸਲਾਜ ॥"},"larivaar":{"gurmukhi":"lwidlwidmnoclyDnDIrbIrslwj]","unicode":"ਲਾਦਿਲਾਦਿਮਨੋਚਲੇਧਨਧੀਰਬੀਰਸਲਾਜ॥"},"translation":{"en":{"bdb":"All this appears as if the traders loading their commodities are coyly running out of the battlefield."},"pu":{"ss":{"gurmukhi":"mwno sUrmy lwj rKdy hoey DIrj dy Dn nUM ld ld ky jw rhy hox।","unicode":"ਮਾਨੋ ਸੂਰਮੇ ਲਾਜ ਰਖਦੇ ਹੋਏ ਧੀਰਜ ਦੇ ਧਨ ਨੂੰ ਲਦ ਲਦ ਕੇ ਜਾ ਰਹੇ ਹੋਣ।"},"ft":{"gurmukhi":"","unicode":""},"bdb":{"gurmukhi":"mwno sUrmy lwj rKdy hoey DIrj dy Dn nUM ld ld ky jw rhy hox।","unicode":"ਮਾਨੋ ਸੂਰਮੇ ਲਾਜ ਰਖਦੇ ਹੋਏ ਧੀਰਜ ਦੇ ਧਨ ਨੂੰ ਲਦ ਲਦ ਕੇ ਜਾ ਰਹੇ ਹੋਣ।"}},"es":{"sn":""},"hi":{}},"transliteration":{"english":"laadh laadh mano chale dhan dheer beer salaaj ||","hindi":"लादि लादि मनो चले धन धीर बीर सलाज ॥","en":"laadh laadh mano chale dhan dheer beer salaaj ||","hi":"लादि लादि मनो चले धन धीर बीर सलाज ॥","ipa":"lɑd̪ lɑd̪ mənɔ t͡ʃəle t̪ən t̪ir bir səlɑd͡ʒ.","ur":"لاد لاد منو چلے دھن دھیِر بیِر سلاج ۔۔"},"pageNo":103,"lineNo":79098,"updated":"2022-12-24 02:22:37","visraam":{"sttm":[],"igurbani":[],"sttm2":[]},"writer":{"writerId":47,"gurmukhi":"gurU goibMd isMG jI","unicode":null,"english":"Guru Gobind Singh Ji"},"raag":{"raagId":52,"gurmukhi":null,"unicode":null,"english":null,"raagWithPage":null}},{"verseId":79099,"shabadId":7682,"verse":{"gurmukhi":"molu bIc iPrY cukwq dlwl Kyq KqMg ]","unicode":"ਮੋਲੁ ਬੀਚ ਫਿਰੈ ਚੁਕਾਤ ਦਲਾਲ ਖੇਤ ਖਤੰਗ ॥"},"larivaar":{"gurmukhi":"molubIciPrYcukwqdlwlKyqKqMg]","unicode":"ਮੋਲੁਬੀਚਫਿਰੈਚੁਕਾਤਦਲਾਲਖੇਤਖਤੰਗ॥"},"translation":{"en":{"bdb":"The arrows of the battlefield are like the agents, who are busy in settling the account of the transaction."},"pu":{"ss":{"gurmukhi":"Xu`DBUmI ivc qIr dlwlw vwg mul cukwaux leI GuMm rhy sn।","unicode":"ਯੁੱਧਭੂਮੀ ਵਿਚ ਤੀਰ ਦਲਾਲਾ ਵਾਗ ਮੁਲ ਚੁਕਾਉਣ ਲਈ ਘੁੰਮ ਰਹੇ ਸਨ।"},"ft":{"gurmukhi":"","unicode":""},"bdb":{"gurmukhi":"Xu`DBUmI ivc qIr dlwlw vwg mul cukwaux leI GuMm rhy sn।","unicode":"ਯੁੱਧਭੂਮੀ ਵਿਚ ਤੀਰ ਦਲਾਲਾ ਵਾਗ ਮੁਲ ਚੁਕਾਉਣ ਲਈ ਘੁੰਮ ਰਹੇ ਸਨ।"}},"es":{"sn":""},"hi":{}},"transliteration":{"english":"mol beech firai chukaat dhalaal khet khata(n)g ||","hindi":"मोलु बीच फिरै चुकात दलाल खेत खतंग ॥","en":"mol beech firai chukaat dhalaal khet khata(n)g ||","hi":"मोलु बीच फिरै चुकात दलाल खेत खतंग ॥","ipa":"mɔl bit͡ʃ fɪræ t͡ʃʊkɑt̪ d̪əlɑl kʰet̪ kʰət̪əŋG.","ur":"مول بیِچ پھرَے چُکات دلال کھےت کھتںگ ۔۔"},"pageNo":103,"lineNo":79099,"updated":"2022-12-24 02:22:37","visraam":{"sttm":[],"igurbani":[],"sttm2":[]},"writer":{"writerId":47,"gurmukhi":"gurU goibMd isMG jI","unicode":null,"english":"Guru Gobind Singh Ji"},"raag":{"raagId":52,"gurmukhi":null,"unicode":null,"english":null,"raagWithPage":null}},{"verseId":79100,"shabadId":7682,"verse":{"gurmukhi":"gwih gwih iPry Pvjin Jwir idrb inKMg ]35]","unicode":"ਗਾਹਿ ਗਾਹਿ ਫਿਰੇ ਫਵਜਨਿ ਝਾਰਿ ਦਿਰਬ ਨਿਖੰਗ ॥੩੫॥"},"larivaar":{"gurmukhi":"gwihgwihiPryPvjinJwiridrbinKMg]35]","unicode":"ਗਾਹਿਗਾਹਿਫਿਰੇਫਵਜਨਿਝਾਰਿਦਿਰਬਨਿਖੰਗ॥੩੫॥"},"translation":{"en":{"bdb":"The armies are fastly moving in the field for settlement and emptying their treasure of quivers.35."},"pu":{"ss":{"gurmukhi":"&Ojw (Xu`D-BUmI ivc) qrkSw qoN (qIrw-rUpI) Dn nUM cukw ky ieDr auDr dOVIAW iPr rhIAW s nw ]35]","unicode":"ਫ਼ੌਜਾ (ਯੁੱਧ-ਭੂਮੀ ਵਿਚ) ਤਰਕਸ਼ਾ ਤੋਂ (ਤੀਰਾ-ਰੂਪੀ) ਧਨ ਨੂੰ ਚੁਕਾ ਕੇ ਇਧਰ ਉਧਰ ਦੌੜੀਆਂ ਫਿਰ ਰਹੀਆਂ ਸ ਨਾ ॥੩੫॥"},"ft":{"gurmukhi":"","unicode":""},"bdb":{"gurmukhi":"&Ojw (Xu`D-BUmI ivc) qrkSw qoN (qIrw-rUpI) Dn nUM cukw ky ieDr auDr dOVIAW iPr rhIAW s nw ]35]","unicode":"ਫ਼ੌਜਾ (ਯੁੱਧ-ਭੂਮੀ ਵਿਚ) ਤਰਕਸ਼ਾ ਤੋਂ (ਤੀਰਾ-ਰੂਪੀ) ਧਨ ਨੂੰ ਚੁਕਾ ਕੇ ਇਧਰ ਉਧਰ ਦੌੜੀਆਂ ਫਿਰ ਰਹੀਆਂ ਸ ਨਾ ॥੩੫॥"}},"es":{"sn":""},"hi":{}},"transliteration":{"english":"gaeh gaeh fire favajan jhaar dhirab nikha(n)g ||35||","hindi":"गाहि गाहि फिरे फवजनि झारि दिरब निखंग ॥३५॥","en":"gaeh gaeh fire favajan jhaar dhirab nikha(n)g ||35||","hi":"गाहि गाहि फिरे फवजनि झारि दिरब निखंग ॥३५॥","ipa":"Gɑh Gɑh fɪre fəʋəd͡ʒən ɖ͡ʐɑr d̪ɪrəb nɪkʰəŋG.3ə5.","ur":"گاه گاه پھرے پھوجن جھار درب نکھںگ ۔۔۳۵۔۔"},"pageNo":103,"lineNo":79100,"updated":"2022-12-24 02:22:37","visraam":{"sttm2":[],"sttm":[],"igurbani":[]},"writer":{"writerId":47,"gurmukhi":"gurU goibMd isMG jI","unicode":null,"english":"Guru Gobind Singh Ji"},"raag":{"raagId":52,"gurmukhi":null,"unicode":null,"english":null,"raagWithPage":null}},{"verseId":79101,"shabadId":7682,"verse":{"gurmukhi":"AMg BMg igry khUM bhurMg rMigq bsqR ]","unicode":"ਅੰਗ ਭੰਗ ਗਿਰੇ ਕਹੂੰ ਬਹੁਰੰਗ ਰੰਗਿਤ ਬਸਤ੍ਰ ॥"},"larivaar":{"gurmukhi":"AMgBMgigrykhUMbhurMgrMigqbsqR]","unicode":"ਅੰਗਭੰਗਗਿਰੇਕਹੂੰਬਹੁਰੰਗਰੰਗਿਤਬਸਤ੍ਰ॥"},"translation":{"en":{"bdb":"Some where multi-coloured garments and chopped limbs are lying."},"pu":{"ss":{"gurmukhi":"ikqy (SrIrw nwloN) kty hoey AMg ifgy pey sn, ikqy bhurMgI bsqR (pey sn)।","unicode":"ਕਿਤੇ (ਸ਼ਰੀਰਾ ਨਾਲੋਂ) ਕਟੇ ਹੋਏ ਅੰਗ ਡਿਗੇ ਪਏ ਸਨ, ਕਿਤੇ ਬਹੁਰੰਗੀ ਬਸਤ੍ਰ (ਪਏ ਸਨ)।"},"ft":{"gurmukhi":"","unicode":""},"bdb":{"gurmukhi":"ikqy (SrIrw nwloN) kty hoey AMg ifgy pey sn, ikqy bhurMgI bsqR (pey sn)।","unicode":"ਕਿਤੇ (ਸ਼ਰੀਰਾ ਨਾਲੋਂ) ਕਟੇ ਹੋਏ ਅੰਗ ਡਿਗੇ ਪਏ ਸਨ, ਕਿਤੇ ਬਹੁਰੰਗੀ ਬਸਤ੍ਰ (ਪਏ ਸਨ)।"}},"es":{"sn":""},"hi":{}},"transliteration":{"english":"a(n)g bha(n)g gire kahoo(n) bahura(n)g ra(n)git basatr ||","hindi":"अंग भंग गिरे कहूँ बहुरंग रंगित बसत्र ॥","en":"a(n)g bha(n)g gire kahoo(n) bahura(n)g ra(n)git basatr ||","hi":"अंग भंग गिरे कहूँ बहुरंग रंगित बसत्र ॥","ipa":"əŋG ɓəŋG Gɪre kəhuŋ bəhʊrəŋG rəŋGɪt̪ bəsət̪ɹ.","ur":"اںگ بھںگ گرے کهُوں بهُرںگ رںگت بستر ۔۔"},"pageNo":103,"lineNo":79101,"updated":"2022-12-24 02:22:37","visraam":{"sttm2":[],"sttm":[],"igurbani":[]},"writer":{"writerId":47,"gurmukhi":"gurU goibMd isMG jI","unicode":null,"english":"Guru Gobind Singh Ji"},"raag":{"raagId":52,"gurmukhi":null,"unicode":null,"english":null,"raagWithPage":null}},{"verseId":79102,"shabadId":7682,"verse":{"gurmukhi":"crm brm suBM khUM rxM ssqR ru AsqR ]","unicode":"ਚਰਮ ਬਰਮ ਸੁਭੰ ਕਹੂੰ ਰਣੰ ਸਸਤ੍ਰ ਰੁ ਅਸਤ੍ਰ ॥"},"larivaar":{"gurmukhi":"crmbrmsuBMkhUMrxMssqRruAsqR]","unicode":"ਚਰਮਬਰਮਸੁਭੰਕਹੂੰਰਣੰਸਸਤ੍ਰਰੁਅਸਤ੍ਰ॥"},"translation":{"en":{"bdb":"Somewhere there are shields and armours and somewhere there only weapons."},"pu":{"ss":{"gurmukhi":"rx-BUmI ivc ikqy Fwl, kvc Aqy ikqy AsqR-SsqR pey SoB rhy sn।","unicode":"ਰਣ-ਭੂਮੀ ਵਿਚ ਕਿਤੇ ਢਾਲ, ਕਵਚ ਅਤੇ ਕਿਤੇ ਅਸਤ੍ਰ-ਸ਼ਸਤ੍ਰ ਪਏ ਸ਼ੋਭ ਰਹੇ ਸਨ।"},"ft":{"gurmukhi":"","unicode":""},"bdb":{"gurmukhi":"rx-BUmI ivc ikqy Fwl, kvc Aqy ikqy AsqR-SsqR pey SoB rhy sn।","unicode":"ਰਣ-ਭੂਮੀ ਵਿਚ ਕਿਤੇ ਢਾਲ, ਕਵਚ ਅਤੇ ਕਿਤੇ ਅਸਤ੍ਰ-ਸ਼ਸਤ੍ਰ ਪਏ ਸ਼ੋਭ ਰਹੇ ਸਨ।"}},"es":{"sn":""},"hi":{}},"transliteration":{"english":"charam baram subha(n) kahoo(n) rana(n) sasatr r asatr ||","hindi":"चरम बरम सुभं कहूँ रणं ससत्र रु असत्र ॥","en":"charam baram subha(n) kahoo(n) rana(n) sasatr r asatr ||","hi":"चरम बरम सुभं कहूँ रणं ससत्र रु असत्र ॥","ipa":"t͡ʃərəm bərəm sʊɓəŋ kəhuŋ rəɳəŋ səsət̪ɹ r əsət̪ɹ.","ur":"چرم برم سُبھں کهُوں رݨں سستر رُ استر ۔۔"},"pageNo":103,"lineNo":79102,"updated":"2022-12-24 02:22:37","visraam":{"sttm2":[],"sttm":[],"igurbani":[]},"writer":{"writerId":47,"gurmukhi":"gurU goibMd isMG jI","unicode":null,"english":"Guru Gobind Singh Ji"},"raag":{"raagId":52,"gurmukhi":null,"unicode":null,"english":null,"raagWithPage":null}},{"verseId":79103,"shabadId":7682,"verse":{"gurmukhi":"muMf quMf Dujw pqwkw tUk twk Aryk ]","unicode":"ਮੁੰਡ ਤੁੰਡ ਧੁਜਾ ਪਤਾਕਾ ਟੂਕ ਟਾਕ ਅਰੇਕ ॥"},"larivaar":{"gurmukhi":"muMfquMfDujwpqwkwtUktwkAryk]","unicode":"ਮੁੰਡਤੁੰਡਧੁਜਾਪਤਾਕਾਟੂਕਟਾਕਅਰੇਕ॥"},"translation":{"en":{"bdb":"Somewhere there are heads, flags and ensigns scattered here and there."},"pu":{"ss":{"gurmukhi":"ikqy isr mUMh Aqy ikqy JMfy-JMfIAW tut-Puty vK vK hoey (ifgy hoey sn)।","unicode":"ਕਿਤੇ ਸਿਰ ਮੂੰਹ ਅਤੇ ਕਿਤੇ ਝੰਡੇ-ਝੰਡੀਆਂ ਟੁਟ-ਫੁਟੇ ਵਖ ਵਖ ਹੋਏ (ਡਿਗੇ ਹੋਏ ਸਨ)।"},"ft":{"gurmukhi":"","unicode":""},"bdb":{"gurmukhi":"ikqy isr mUMh Aqy ikqy JMfy-JMfIAW tut-Puty vK vK hoey (ifgy hoey sn)।","unicode":"ਕਿਤੇ ਸਿਰ ਮੂੰਹ ਅਤੇ ਕਿਤੇ ਝੰਡੇ-ਝੰਡੀਆਂ ਟੁਟ-ਫੁਟੇ ਵਖ ਵਖ ਹੋਏ (ਡਿਗੇ ਹੋਏ ਸਨ)।"}},"es":{"sn":""},"hi":{}},"transliteration":{"english":"mu(n)dd tu(n)dd dhujaa pataakaa Took Taak arek ||","hindi":"मुँड तुँड धुजा पताका टूक टाक अरेक ॥","en":"mu(n)dd tu(n)dd dhujaa pataakaa Took Taak arek ||","hi":"मुँड तुँड धुजा पताका टूक टाक अरेक ॥","ipa":"mʊŋɖ t̪ʊŋɖ t̪ʊd͡ʒɑ pət̪ɑkɑ ʈuk ʈɑk ərek.","ur":"مُںڈ تُںڈ دھُجا پتاکا ٹُوک ٹاک ارےک ۔۔"},"pageNo":103,"lineNo":79103,"updated":"2022-12-24 02:22:37","visraam":{"sttm":[],"igurbani":[],"sttm2":[]},"writer":{"writerId":47,"gurmukhi":"gurU goibMd isMG jI","unicode":null,"english":"Guru Gobind Singh Ji"},"raag":{"raagId":52,"gurmukhi":null,"unicode":null,"english":null,"raagWithPage":null}},{"verseId":79104,"shabadId":7682,"verse":{"gurmukhi":"jUJ jUJ pry sbY Air bwicXo nhI eyk ]36]","unicode":"ਜੂਝ ਜੂਝ ਪਰੇ ਸਬੈ ਅਰਿ ਬਾਚਿਯੋ ਨਹੀ ਏਕ ॥੩੬॥"},"larivaar":{"gurmukhi":"jUJjUJprysbYAirbwicXonhIeyk]36]","unicode":"ਜੂਝਜੂਝਪਰੇਸਬੈਅਰਿਬਾਚਿਯੋਨਹੀਏਕ॥੩੬॥"},"translation":{"en":{"bdb":"In the battlefield all the enemies have fallen down while fighting and none has been left alive.36."},"pu":{"ss":{"gurmukhi":"swry vYrI lV lV ky ifgy pey sn Aqy koeI iek vI bicAw nhIN sI ]36]","unicode":"ਸਾਰੇ ਵੈਰੀ ਲੜ ਲੜ ਕੇ ਡਿਗੇ ਪਏ ਸਨ ਅਤੇ ਕੋਈ ਇਕ ਵੀ ਬਚਿਆ ਨਹੀਂ ਸੀ ॥੩੬॥"},"ft":{"gurmukhi":"","unicode":""},"bdb":{"gurmukhi":"swry vYrI lV lV ky ifgy pey sn Aqy koeI iek vI bicAw nhIN sI ]36]","unicode":"ਸਾਰੇ ਵੈਰੀ ਲੜ ਲੜ ਕੇ ਡਿਗੇ ਪਏ ਸਨ ਅਤੇ ਕੋਈ ਇਕ ਵੀ ਬਚਿਆ ਨਹੀਂ ਸੀ ॥੩੬॥"}},"es":{"sn":""},"hi":{}},"transliteration":{"english":"joojh joojh pare sabai ar baachiyo nahee ek ||36||","hindi":"जूझ जूझ परे सबै अरि बाचियो नही एक ॥३६॥","en":"joojh joojh pare sabai ar baachiyo nahee ek ||36||","hi":"जूझ जूझ परे सबै अरि बाचियो नही एक ॥३६॥","ipa":"d͡ʒuɖ͡ʐ d͡ʒuɖ͡ʐ pəre səbæ ər bɑt͡ʃɪjɔ nəhi eek.3ə6.","ur":"جُوجھ جُوجھ پرے سبَے ار باچےو نهیِ اےک ۔۔۳۶۔۔"},"pageNo":103,"lineNo":79104,"updated":"2022-12-24 02:22:37","visraam":{"sttm2":[],"sttm":[],"igurbani":[]},"writer":{"writerId":47,"gurmukhi":"gurU goibMd isMG jI","unicode":null,"english":"Guru Gobind Singh Ji"},"raag":{"raagId":52,"gurmukhi":null,"unicode":null,"english":null,"raagWithPage":null}},{"verseId":79105,"shabadId":7682,"verse":{"gurmukhi":"kop kY mihKys dwno DweIXo iqh kwl ]","unicode":"ਕੋਪ ਕੈ ਮਹਿਖੇਸ ਦਾਨੋ ਧਾਈਯੋ ਤਿਹ ਕਾਲ ॥"},"larivaar":{"gurmukhi":"kopkYmihKysdwnoDweIXoiqhkwl]","unicode":"ਕੋਪਕੈਮਹਿਖੇਸਦਾਨੋਧਾਈਯੋਤਿਹਕਾਲ॥"},"translation":{"en":{"bdb":"Then in great ire, the demon Mahishasura marched forward."},"pu":{"ss":{"gurmukhi":"aus vyly kRoDvwn ho ky mihKwsur dYNq ny Dwvw kIqw।","unicode":"ਉਸ ਵੇਲੇ ਕ੍ਰੋਧਵਾਨ ਹੋ ਕੇ ਮਹਿਖਾਸੁਰ ਦੈਂਤ ਨੇ ਧਾਵਾ ਕੀਤਾ।"},"ft":{"gurmukhi":"","unicode":""},"bdb":{"gurmukhi":"aus vyly kRoDvwn ho ky mihKwsur dYNq ny Dwvw kIqw।","unicode":"ਉਸ ਵੇਲੇ ਕ੍ਰੋਧਵਾਨ ਹੋ ਕੇ ਮਹਿਖਾਸੁਰ ਦੈਂਤ ਨੇ ਧਾਵਾ ਕੀਤਾ।"}},"es":{"sn":""},"hi":{}},"transliteration":{"english":"kop kai mahikhes dhaano dhaieeyo teh kaal ||","hindi":"कोप कै महिखेस दानो धाईयो तिह काल ॥","en":"kop kai mahikhes dhaano dhaieeyo teh kaal ||","hi":"कोप कै महिखेस दानो धाईयो तिह काल ॥","ipa":"kɔp kæ məhɪkʰes d̪ɑnɔ t̪ɑeijɔ t̪ɪh kɑl.","ur":"کوپ کَے مهِکھےس دانو دھاایےو ته کال ۔۔"},"pageNo":103,"lineNo":79105,"updated":"2022-12-24 02:22:37","visraam":{"sttm2":[],"sttm":[],"igurbani":[]},"writer":{"writerId":47,"gurmukhi":"gurU goibMd isMG jI","unicode":null,"english":"Guru Gobind Singh Ji"},"raag":{"raagId":52,"gurmukhi":null,"unicode":null,"english":null,"raagWithPage":null}},{"verseId":79106,"shabadId":7682,"verse":{"gurmukhi":"AsqR ssqR sMBwr sUro rUp kY ibkrwl ]","unicode":"ਅਸਤ੍ਰ ਸਸਤ੍ਰ ਸੰਭਾਰ ਸੂਰੋ ਰੂਪ ਕੈ ਬਿਕਰਾਲ ॥"},"larivaar":{"gurmukhi":"AsqRssqRsMBwrsUrorUpkYibkrwl]","unicode":"ਅਸਤ੍ਰਸਸਤ੍ਰਸੰਭਾਰਸੂਰੋਰੂਪਕੈਬਿਕਰਾਲ॥"},"translation":{"en":{"bdb":"He appeared in a frightful form and held up all his weapons and arms."},"pu":{"ss":{"gurmukhi":"aus ny AsqR SsqR Dwrn kr ky iBAwnk rUp bxw ilAw।","unicode":"ਉਸ ਨੇ ਅਸਤ੍ਰ ਸ਼ਸਤ੍ਰ ਧਾਰਨ ਕਰ ਕੇ ਭਿਆਨਕ ਰੂਪ ਬਣਾ ਲਿਆ।"},"ft":{"gurmukhi":"","unicode":""},"bdb":{"gurmukhi":"aus ny AsqR SsqR Dwrn kr ky iBAwnk rUp bxw ilAw।","unicode":"ਉਸ ਨੇ ਅਸਤ੍ਰ ਸ਼ਸਤ੍ਰ ਧਾਰਨ ਕਰ ਕੇ ਭਿਆਨਕ ਰੂਪ ਬਣਾ ਲਿਆ।"}},"es":{"sn":""},"hi":{}},"transliteration":{"english":"asatr sasatr sa(n)bhaar sooro roop kai bikaraal ||","hindi":"असत्र ससत्र संभार सूरो रूप कै बिकराल ॥","en":"asatr sasatr sa(n)bhaar sooro roop kai bikaraal ||","hi":"असत्र ससत्र संभार सूरो रूप कै बिकराल ॥","ipa":"əsət̪ɹ səsət̪ɹ səŋɓɑr surɔ rup kæ bɪkərɑl.","ur":"استر سستر سںبھار سُورو رُوپ کَے بکرال ۔۔"},"pageNo":103,"lineNo":79106,"updated":"2022-12-24 02:22:37","visraam":{"sttm":[],"igurbani":[],"sttm2":[]},"writer":{"writerId":47,"gurmukhi":"gurU goibMd isMG jI","unicode":null,"english":"Guru Gobind Singh Ji"},"raag":{"raagId":52,"gurmukhi":null,"unicode":null,"english":null,"raagWithPage":null}},{"verseId":79107,"shabadId":7682,"verse":{"gurmukhi":"kwl pwix ikRpwx lY iqh mwirXo qqkwl ]","unicode":"ਕਾਲ ਪਾਣਿ ਕ੍ਰਿਪਾਣ ਲੈ ਤਿਹ ਮਾਰਿਯੋ ਤਤਕਾਲ ॥"},"larivaar":{"gurmukhi":"kwlpwixikRpwxlYiqhmwirXoqqkwl]","unicode":"ਕਾਲਪਾਣਿਕ੍ਰਿਪਾਣਲੈਤਿਹਮਾਰਿਯੋਤਤਕਾਲ॥"},"translation":{"en":{"bdb":"The goddess Kalka took her sword in her hand and killed him instantly."},"pu":{"ss":{"gurmukhi":"kwlI dyvI ny h`Q ivc ikRpwn lY ky aus nUM qurMq mwr id`qw।","unicode":"ਕਾਲੀ ਦੇਵੀ ਨੇ ਹੱਥ ਵਿਚ ਕ੍ਰਿਪਾਨ ਲੈ ਕੇ ਉਸ ਨੂੰ ਤੁਰੰਤ ਮਾਰ ਦਿੱਤਾ।"},"ft":{"gurmukhi":"","unicode":""},"bdb":{"gurmukhi":"kwlI dyvI ny h`Q ivc ikRpwn lY ky aus nUM qurMq mwr id`qw।","unicode":"ਕਾਲੀ ਦੇਵੀ ਨੇ ਹੱਥ ਵਿਚ ਕ੍ਰਿਪਾਨ ਲੈ ਕੇ ਉਸ ਨੂੰ ਤੁਰੰਤ ਮਾਰ ਦਿੱਤਾ।"}},"es":{"sn":""},"hi":{}},"transliteration":{"english":"kaal paan kirapaan lai teh maariyo tatakaal ||","hindi":"काल पाणि कृपाण लै तिह मारियो ततकाल ॥","en":"kaal paan kirapaan lai teh maariyo tatakaal ||","hi":"काल पाणि कृपाण लै तिह मारियो ततकाल ॥","ipa":"kɑl pɑɳ kɪɹəpɑɳ læ t̪ɪh mɑrɪjɔ t̪ət̪əkɑl.","ur":"کال پاݨ کرپاݨ لَے ته مارےو تتکال ۔۔"},"pageNo":103,"lineNo":79107,"updated":"2022-12-24 02:22:37","visraam":{"sttm2":[],"sttm":[],"igurbani":[]},"writer":{"writerId":47,"gurmukhi":"gurU goibMd isMG jI","unicode":null,"english":"Guru Gobind Singh Ji"},"raag":{"raagId":52,"gurmukhi":null,"unicode":null,"english":null,"raagWithPage":null}},{"verseId":79108,"shabadId":7682,"verse":{"gurmukhi":"joiq joiq ibKY imlI qj bRhmrMiDR auqwl ]37]","unicode":"ਜੋਤਿ ਜੋਤਿ ਬਿਖੈ ਮਿਲੀ ਤਜ ਬ੍ਰਹਮਰੰਧ੍ਰਿ ਉਤਾਲ ॥੩੭॥"},"larivaar":{"gurmukhi":"joiqjoiqibKYimlIqjbRhmrMiDRauqwl]37]","unicode":"ਜੋਤਿਜੋਤਿਬਿਖੈਮਿਲੀਤਜਬ੍ਰਹਮਰੰਧ੍ਰਿਉਤਾਲ॥੩੭॥"},"translation":{"en":{"bdb":"His soul left Brahmrandhir (life-channel of Dasam Dyar) and merged in Divine Light.37."},"pu":{"ss":{"gurmukhi":"(dYNq dI) joiq aus dy dsm-duAwr ('bRhmrMiDR') C`f ky CyqI nwl prm joiq ivc ivlIn ho geI ]37]","unicode":"(ਦੈਂਤ ਦੀ) ਜੋਤਿ ਉਸ ਦੇ ਦਸਮ-ਦੁਆਰ ('ਬ੍ਰਹਮਰੰਧ੍ਰਿ') ਛੱਡ ਕੇ ਛੇਤੀ ਨਾਲ ਪਰਮ ਜੋਤਿ ਵਿਚ ਵਿਲੀਨ ਹੋ ਗਈ ॥੩੭॥"},"ft":{"gurmukhi":"","unicode":""},"bdb":{"gurmukhi":"(dYNq dI) joiq aus dy dsm-duAwr ('bRhmrMiDR') C`f ky CyqI nwl prm joiq ivc ivlIn ho geI ]37]","unicode":"(ਦੈਂਤ ਦੀ) ਜੋਤਿ ਉਸ ਦੇ ਦਸਮ-ਦੁਆਰ ('ਬ੍ਰਹਮਰੰਧ੍ਰਿ') ਛੱਡ ਕੇ ਛੇਤੀ ਨਾਲ ਪਰਮ ਜੋਤਿ ਵਿਚ ਵਿਲੀਨ ਹੋ ਗਈ ॥੩੭॥"}},"es":{"sn":""},"hi":{}},"transliteration":{"english":"jot jot bikhai milee taj brahamara(n)dhr utaal ||37||","hindi":"जोति जोति बिखै मिली तज ब्रहमरंधृ उताल ॥३७॥","en":"jot jot bikhai milee taj brahamara(n)dhr utaal ||37||","hi":"जोति जोति बिखै मिली तज ब्रहमरंधृ उताल ॥३७॥","ipa":"d͡ʒɔt̪ d͡ʒɔt̪ bɪkʰæ mɪli t̪əd͡ʒ bɹəhəmərəŋt̪ɪɹ oʊt̪ɑl.3ə7.","ur":"جوت جوت بکھَے ملیِ تج برهمرںدھر اُتال ۔۔۳۷۔۔"},"pageNo":103,"lineNo":79108,"updated":"2022-12-24 02:22:37","visraam":{"sttm2":[],"sttm":[],"igurbani":[]},"writer":{"writerId":47,"gurmukhi":"gurU goibMd isMG jI","unicode":null,"english":"Guru Gobind Singh Ji"},"raag":{"raagId":52,"gurmukhi":null,"unicode":null,"english":null,"raagWithPage":null}},{"verseId":79109,"shabadId":7683,"verse":{"gurmukhi":"dohrw ]","unicode":"ਦੋਹਰਾ ॥"},"larivaar":{"gurmukhi":"dohrw]","unicode":"ਦੋਹਰਾ॥"},"translation":{"en":{"bdb":"DOHRA"},"pu":{"ss":{"gurmukhi":"dohrw:","unicode":"ਦੋਹਰਾ:"},"ft":{"gurmukhi":"","unicode":""},"bdb":{"gurmukhi":"dohrw:","unicode":"ਦੋਹਰਾ:"}},"es":{"sn":""},"hi":{}},"transliteration":{"english":"dhoharaa ||","hindi":"दोहरा ॥","en":"dhoharaa ||","hi":"दोहरा ॥","ipa":"d̪ɔhərɑ.","ur":"دوهرا ۔۔"},"pageNo":103,"lineNo":79109,"updated":"2022-12-24 02:22:37","visraam":{"sttm":[],"igurbani":[],"sttm2":[]},"writer":{"writerId":47,"gurmukhi":"gurU goibMd isMG jI","unicode":null,"english":"Guru Gobind Singh Ji"},"raag":{"raagId":52,"gurmukhi":null,"unicode":null,"english":null,"raagWithPage":null}},{"verseId":79110,"shabadId":7683,"verse":{"gurmukhi":"mihKwsur kh mwr kir pRPulq BI jg mwie ]","unicode":"ਮਹਿਖਾਸੁਰ ਕਹ ਮਾਰ ਕਰਿ ਪ੍ਰਫੁਲਤ ਭੀ ਜਗ ਮਾਇ ॥"},"larivaar":{"gurmukhi":"mihKwsurkhmwrkirpRPulqBIjgmwie]","unicode":"ਮਹਿਖਾਸੁਰਕਹਮਾਰਕਰਿਪ੍ਰਫੁਲਤਭੀਜਗਮਾਇ॥"},"translation":{"en":{"bdb":"After killing Mahishasura, the Mother of the world was greatly pleased."},"pu":{"ss":{"gurmukhi":"mihKwsur nUM mwr ky dyvI bhuq pRsMn hoeI।","unicode":"ਮਹਿਖਾਸੁਰ ਨੂੰ ਮਾਰ ਕੇ ਦੇਵੀ ਬਹੁਤ ਪ੍ਰਸੰਨ ਹੋਈ।"},"ft":{"gurmukhi":"","unicode":""},"bdb":{"gurmukhi":"mihKwsur nUM mwr ky dyvI bhuq pRsMn hoeI।","unicode":"ਮਹਿਖਾਸੁਰ ਨੂੰ ਮਾਰ ਕੇ ਦੇਵੀ ਬਹੁਤ ਪ੍ਰਸੰਨ ਹੋਈ।"}},"es":{"sn":""},"hi":{}},"transliteration":{"english":"mahikhaasur keh maar kar prafulat bhee jag mai ||","hindi":"महिखासुर कह मार करि प्रफुलत भी जग माइ ॥","en":"mahikhaasur keh maar kar prafulat bhee jag mai ||","hi":"महिखासुर कह मार करि प्रफुलत भी जग माइ ॥","ipa":"məhɪkʰɑsʊr kəh mɑr kər pɹəfʊlət̪ ɓi d͡ʒəG mɑeɪ.","ur":"مهِکھاسر که مار کر پرپھلت بھیِ جگ ماا ۔۔"},"pageNo":103,"lineNo":79110,"updated":"2022-12-24 02:22:37","visraam":{"sttm2":[],"sttm":[],"igurbani":[]},"writer":{"writerId":47,"gurmukhi":"gurU goibMd isMG jI","unicode":null,"english":"Guru Gobind Singh Ji"},"raag":{"raagId":52,"gurmukhi":null,"unicode":null,"english":null,"raagWithPage":null}},{"verseId":79111,"shabadId":7683,"verse":{"gurmukhi":"qw idn qy mihKy blY dyq jgq suK pwie ]38]","unicode":"ਤਾ ਦਿਨ ਤੇ ਮਹਿਖੇ ਬਲੈ ਦੇਤ ਜਗਤ ਸੁਖ ਪਾਇ ॥੩੮॥"},"larivaar":{"gurmukhi":"qwidnqymihKyblYdyqjgqsuKpwie]38]","unicode":"ਤਾਦਿਨਤੇਮਹਿਖੇਬਲੈਦੇਤਜਗਤਸੁਖਪਾਇ॥੩੮॥"},"translation":{"en":{"bdb":"And from that day the whole world gives the sacrifice of the animals for the attainment of peace.38."},"pu":{"ss":{"gurmukhi":"aus idn qoN suK pRwpqI leI jgq ivc Joty dI blI id`qI jwx lgI ]38]","unicode":"ਉਸ ਦਿਨ ਤੋਂ ਸੁਖ ਪ੍ਰਾਪਤੀ ਲਈ ਜਗਤ ਵਿਚ ਝੋਟੇ ਦੀ ਬਲੀ ਦਿੱਤੀ ਜਾਣ ਲਗੀ ॥੩੮॥"},"ft":{"gurmukhi":"","unicode":""},"bdb":{"gurmukhi":"aus idn qoN suK pRwpqI leI jgq ivc Joty dI blI id`qI jwx lgI ]38]","unicode":"ਉਸ ਦਿਨ ਤੋਂ ਸੁਖ ਪ੍ਰਾਪਤੀ ਲਈ ਜਗਤ ਵਿਚ ਝੋਟੇ ਦੀ ਬਲੀ ਦਿੱਤੀ ਜਾਣ ਲਗੀ ॥੩੮॥"}},"es":{"sn":""},"hi":{}},"transliteration":{"english":"taa dhin te mahikhe balai dhet jagat sukh pai ||38||","hindi":"ता दिन ते महिखे बलै देत जगत सुख पाइ ॥३८॥","en":"taa dhin te mahikhe balai dhet jagat sukh pai ||38||","hi":"ता दिन ते महिखे बलै देत जगत सुख पाइ ॥३८॥","ipa":"t̪ɑ d̪ɪn t̪e məhɪkʰe bəlæ d̪et̪ d͡ʒəGət̪ sʊkʰ pɑeɪ.3ə8.","ur":"تا دن تے مهِکھے بلَے دےت جگت سُکھ پاا ۔۔۳۸۔۔"},"pageNo":103,"lineNo":79111,"updated":"2022-12-24 02:22:37","visraam":{"sttm":[],"igurbani":[],"sttm2":[]},"writer":{"writerId":47,"gurmukhi":"gurU goibMd isMG jI","unicode":null,"english":"Guru Gobind Singh Ji"},"raag":{"raagId":52,"gurmukhi":null,"unicode":null,"english":null,"raagWithPage":null}},{"verseId":79112,"shabadId":7683,"verse":{"gurmukhi":"ieiq sRI bicqR nwtky cMfI cirqRy mihKwsur bDh pRQm iDAwie sMpUrnMm squ suBm squ ]1]","unicode":"ਇਤਿ ਸ੍ਰੀ ਬਚਿਤ੍ਰ ਨਾਟਕੇ ਚੰਡੀ ਚਰਿਤ੍ਰੇ ਮਹਿਖਾਸੁਰ ਬਧਹ ਪ੍ਰਥਮ ਧਿਆਇ ਸੰਪੂਰਨੰਮ ਸਤੁ ਸੁਭਮ ਸਤੁ ॥੧॥"},"larivaar":{"gurmukhi":"ieiqsRIbicqRnwtkycMfIcirqRymihKwsurbDhpRQmiDAwiesMpUrnMmsqusuBmsqu]1]","unicode":"ਇਤਿਸ੍ਰੀਬਚਿਤ੍ਰਨਾਟਕੇਚੰਡੀਚਰਿਤ੍ਰੇਮਹਿਖਾਸੁਰਬਧਹਪ੍ਰਥਮਧਿਆਇਸੰਪੂਰਨੰਮਸਤੁਸੁਭਮਸਤੁ॥੧॥"},"translation":{"en":{"bdb":"Here ends the First Chapter entitled ‘Killing of Mahishasura’ of Chandi Charitra in BACHITTAR NATAK.1."},"pu":{"ss":{"gurmukhi":"ieQy sRI bicqR nwtk dy cMfI cirqR pRsMg dy 'mihKwsur-bD' nw dy pihly AiDAwie dI suB smwpqI ]1]","unicode":"ਇਥੇ ਸ੍ਰੀ ਬਚਿਤ੍ਰ ਨਾਟਕ ਦੇ ਚੰਡੀ ਚਰਿਤ੍ਰ ਪ੍ਰਸੰਗ ਦੇ 'ਮਹਿਖਾਸੁਰ-ਬਧ' ਨਾ ਦੇ ਪਹਿਲੇ ਅਧਿਆਇ ਦੀ ਸੁਭ ਸਮਾਪਤੀ ॥੧॥"},"ft":{"gurmukhi":"","unicode":""},"bdb":{"gurmukhi":"ieQy sRI bicqR nwtk dy cMfI cirqR pRsMg dy 'mihKwsur-bD' nw dy pihly AiDAwie dI suB smwpqI ]1]","unicode":"ਇਥੇ ਸ੍ਰੀ ਬਚਿਤ੍ਰ ਨਾਟਕ ਦੇ ਚੰਡੀ ਚਰਿਤ੍ਰ ਪ੍ਰਸੰਗ ਦੇ 'ਮਹਿਖਾਸੁਰ-ਬਧ' ਨਾ ਦੇ ਪਹਿਲੇ ਅਧਿਆਇ ਦੀ ਸੁਭ ਸਮਾਪਤੀ ॥੧॥"}},"es":{"sn":""},"hi":{}},"transliteration":{"english":"eit sree bachitr naaTake cha(n)ddee charitre mahikhaasur badheh pratham dhiaai sa(n)poorana(n)m sat subham sat ||1||","hindi":"इति स्री बचित्र नाटके चंडी चरित्रे महिखासुर बधह प्रथम धिआइ संपूरनंम सतु सुभम सतु ॥१॥","en":"eit sree bachitr naaTake cha(n)ddee charitre mahikhaasur badheh pratham dhiaai sa(n)poorana(n)m sat subham sat ||1||","hi":"इति स्री बचित्र नाटके चंडी चरित्रे महिखासुर बधह प्रथम धिआइ संपूरनंम सतु सुभम सतु ॥१॥","ipa":"eɪt̪ sɹi bət͡ʃɪt̪ɹ nɑʈəke t͡ʃəŋɖi t͡ʃərɪt̪ɹe məhɪkʰɑsʊr bət̪əh pɹət̪ʰəm t̪ɪəɑeɪ səŋpurənəŋm sət̪ sʊɓəm sət̪.1.","ur":"ِات سریِ بچتر ناٹکے چںڈیِ چرِترے مهِکھاسر بدھه پرتھم دھآا سمپُورنںم ست سُبھم ست ۔۔۱۔۔"},"pageNo":103,"lineNo":79112,"updated":"2022-12-24 02:22:37","visraam":{"sttm2":[],"sttm":[],"igurbani":[]},"writer":{"writerId":47,"gurmukhi":"gurU goibMd isMG jI","unicode":null,"english":"Guru Gobind Singh Ji"},"raag":{"raagId":52,"gurmukhi":null,"unicode":null,"english":null,"raagWithPage":null}},{"verseId":79113,"shabadId":7684,"verse":{"gurmukhi":"AQ DUmnYn juD kQn ]","unicode":"ਅਥ ਧੂਮਨੈਨ ਜੁਧ ਕਥਨ ॥"},"larivaar":{"gurmukhi":"AQDUmnYnjuDkQn]","unicode":"ਅਥਧੂਮਨੈਨਜੁਧਕਥਨ॥"},"translation":{"en":{"bdb":"Here begins the description of the war with Dhumar Nain :"},"pu":{"ss":{"gurmukhi":"hux DUmR nYn dy Xu`D dw kQn","unicode":"ਹੁਣ ਧੂਮ੍ਰ ਨੈਨ ਦੇ ਯੁੱਧ ਦਾ ਕਥਨ"},"ft":{"gurmukhi":"","unicode":""},"bdb":{"gurmukhi":"hux DUmR nYn dy Xu`D dw kQn","unicode":"ਹੁਣ ਧੂਮ੍ਰ ਨੈਨ ਦੇ ਯੁੱਧ ਦਾ ਕਥਨ"}},"es":{"sn":""},"hi":{}},"transliteration":{"english":"ath dhoomanain judh kathan ||","hindi":"अथ धूमनैन जुध कथन ॥","en":"ath dhoomanain judh kathan ||","hi":"अथ धूमनैन जुध कथन ॥","ipa":"ət̪ʰ t̪umənæn d͡ʒʊt̪ə̀ kət̪ʰən.","ur":"اتھ دھُومنَےن جُدھ کتھن ۔۔"},"pageNo":103,"lineNo":79113,"updated":"2022-12-24 02:22:37","visraam":{"sttm2":[],"sttm":[],"igurbani":[]},"writer":{"writerId":47,"gurmukhi":"gurU goibMd isMG jI","unicode":null,"english":"Guru Gobind Singh Ji"},"raag":{"raagId":52,"gurmukhi":null,"unicode":null,"english":null,"raagWithPage":null}},{"verseId":79114,"shabadId":7684,"verse":{"gurmukhi":"kulk CMd ]","unicode":"ਕੁਲਕ ਛੰਦ ॥"},"larivaar":{"gurmukhi":"kulkCMd]","unicode":"ਕੁਲਕਛੰਦ॥"},"translation":{"en":{"bdb":"KULAK STANZA"},"pu":{"ss":{"gurmukhi":"kulk CMd:","unicode":"ਕੁਲਕ ਛੰਦ:"},"ft":{"gurmukhi":"","unicode":""},"bdb":{"gurmukhi":"kulk CMd:","unicode":"ਕੁਲਕ ਛੰਦ:"}},"es":{"sn":""},"hi":{}},"transliteration":{"english":"kulak chha(n)dh ||","hindi":"कुलक छंद ॥","en":"kulak chha(n)dh ||","hi":"कुलक छंद ॥","ipa":"kʊlək ɕəŋd̪.","ur":"کُلک چھںد ۔۔"},"pageNo":103,"lineNo":79114,"updated":"2022-12-24 02:22:37","visraam":{"sttm":[],"igurbani":[],"sttm2":[]},"writer":{"writerId":47,"gurmukhi":"gurU goibMd isMG jI","unicode":null,"english":"Guru Gobind Singh Ji"},"raag":{"raagId":52,"gurmukhi":null,"unicode":null,"english":null,"raagWithPage":null}},{"verseId":79115,"shabadId":7684,"verse":{"gurmukhi":"dyv su qb gwjIX ]","unicode":"ਦੇਵ ਸੁ ਤਬ ਗਾਜੀਯ ॥"},"larivaar":{"gurmukhi":"dyvsuqbgwjIX]","unicode":"ਦੇਵਸੁਤਬਗਾਜੀਯ॥"},"translation":{"en":{"bdb":""},"pu":{"ss":{"gurmukhi":"qdoN dyvI gjx lgI।","unicode":"ਤਦੋਂ ਦੇਵੀ ਗਜਣ ਲਗੀ।"},"ft":{"gurmukhi":"","unicode":""},"bdb":{"gurmukhi":"qdoN dyvI gjx lgI।","unicode":"ਤਦੋਂ ਦੇਵੀ ਗਜਣ ਲਗੀ।"}},"es":{"sn":""},"hi":{}},"transliteration":{"english":"dhev su tab gaajeey ||","hindi":"देव सु तब गाजीय ॥","en":"dhev su tab gaajeey ||","hi":"देव सु तब गाजीय ॥","ipa":"d̪eʋ s t̪əb Gɑd͡ʒij.","ur":"دےو سُ تب گاجیِے ۔۔"},"pageNo":103,"lineNo":79115,"updated":"2022-12-24 02:22:37","visraam":{"sttm2":[],"sttm":[],"igurbani":[]},"writer":{"writerId":47,"gurmukhi":"gurU goibMd isMG jI","unicode":null,"english":"Guru Gobind Singh Ji"},"raag":{"raagId":52,"gurmukhi":null,"unicode":null,"english":null,"raagWithPage":null}},{"verseId":79116,"shabadId":7684,"verse":{"gurmukhi":"Anhd bwjIX ]","unicode":"ਅਨਹਦ ਬਾਜੀਯ ॥"},"larivaar":{"gurmukhi":"AnhdbwjIX]","unicode":"ਅਨਹਦਬਾਜੀਯ॥"},"translation":{"en":{"bdb":"Then the goddess roared and there was continuous intonation."},"pu":{"ss":{"gurmukhi":"lgwqwr vwjy vjx lgy।","unicode":"ਲਗਾਤਾਰ ਵਾਜੇ ਵਜਣ ਲਗੇ।"},"ft":{"gurmukhi":"","unicode":""},"bdb":{"gurmukhi":"lgwqwr vwjy vjx lgy।","unicode":"ਲਗਾਤਾਰ ਵਾਜੇ ਵਜਣ ਲਗੇ।"}},"es":{"sn":""},"hi":{}},"transliteration":{"english":"anahadh baajeey ||","hindi":"अनहद बाजीय ॥","en":"anahadh baajeey ||","hi":"अनहद बाजीय ॥","ipa":"ənəhəd̪ bɑd͡ʒij.","ur":"انهد باجیِے ۔۔"},"pageNo":103,"lineNo":79116,"updated":"2022-12-24 02:22:37","visraam":{"sttm2":[],"sttm":[],"igurbani":[]},"writer":{"writerId":47,"gurmukhi":"gurU goibMd isMG jI","unicode":null,"english":"Guru Gobind Singh Ji"},"raag":{"raagId":52,"gurmukhi":null,"unicode":null,"english":null,"raagWithPage":null}},{"verseId":79117,"shabadId":7684,"verse":{"gurmukhi":"BeI bDweI ]","unicode":"ਭਈ ਬਧਾਈ ॥"},"larivaar":{"gurmukhi":"BeIbDweI]","unicode":"ਭਈਬਧਾਈ॥"},"translation":{"en":{"bdb":""},"pu":{"ss":{"gurmukhi":"sB nUM KuSI dyx vwlI","unicode":"ਸਭ ਨੂੰ ਖੁਸ਼ੀ ਦੇਣ ਵਾਲੀ"},"ft":{"gurmukhi":"","unicode":""},"bdb":{"gurmukhi":"sB nUM KuSI dyx vwlI","unicode":"ਸਭ ਨੂੰ ਖੁਸ਼ੀ ਦੇਣ ਵਾਲੀ"}},"es":{"sn":""},"hi":{}},"transliteration":{"english":"bhiee badhaiee ||","hindi":"भई बधाई ॥","en":"bhiee badhaiee ||","hi":"भई बधाई ॥","ipa":"ɓei bət̪ɑei.","ur":"بھای بدھاای ۔۔"},"pageNo":103,"lineNo":79117,"updated":"2022-12-24 02:22:37","visraam":{"sttm2":[],"sttm":[],"igurbani":[]},"writer":{"writerId":47,"gurmukhi":"gurU goibMd isMG jI","unicode":null,"english":"Guru Gobind Singh Ji"},"raag":{"raagId":52,"gurmukhi":null,"unicode":null,"english":null,"raagWithPage":null}},{"verseId":79118,"shabadId":7684,"verse":{"gurmukhi":"sB suKdweI ]1]39]","unicode":"ਸਭ ਸੁਖਦਾਈ ॥੧॥੩੯॥"},"larivaar":{"gurmukhi":"sBsuKdweI]1]39]","unicode":"ਸਭਸੁਖਦਾਈ॥੧॥੩੯॥"},"translation":{"en":{"bdb":"All were delighted and felt comfortable.1.39."},"pu":{"ss":{"gurmukhi":"vDweI hox lgI ]1]39]","unicode":"ਵਧਾਈ ਹੋਣ ਲਗੀ ॥੧॥੩੯॥"},"ft":{"gurmukhi":"","unicode":""},"bdb":{"gurmukhi":"vDweI hox lgI ]1]39]","unicode":"ਵਧਾਈ ਹੋਣ ਲਗੀ ॥੧॥੩੯॥"}},"es":{"sn":""},"hi":{}},"transliteration":{"english":"sabh sukhadhaiee ||1||39||","hindi":"सभ सुखदाई ॥१॥३९॥","en":"sabh sukhadhaiee ||1||39||","hi":"सभ सुखदाई ॥१॥३९॥","ipa":"səɓ sʊkʰəd̪ɑei.1.3ə9.","ur":"سبھ سُکھداای ۔۔۱۔۔۳۹۔۔"},"pageNo":103,"lineNo":79118,"updated":"2022-12-24 02:22:37","visraam":{"sttm2":[],"sttm":[],"igurbani":[]},"writer":{"writerId":47,"gurmukhi":"gurU goibMd isMG jI","unicode":null,"english":"Guru Gobind Singh Ji"},"raag":{"raagId":52,"gurmukhi":null,"unicode":null,"english":null,"raagWithPage":null}},{"verseId":79119,"shabadId":7684,"verse":{"gurmukhi":"duMdB bwjy ]","unicode":"ਦੁੰਦਭ ਬਾਜੇ ॥"},"larivaar":{"gurmukhi":"duMdBbwjy]","unicode":"ਦੁੰਦਭਬਾਜੇ॥"},"translation":{"en":{"bdb":""},"pu":{"ss":{"gurmukhi":"DONsy vjx lgy","unicode":"ਧੌਂਸੇ ਵਜਣ ਲਗੇ"},"ft":{"gurmukhi":"","unicode":""},"bdb":{"gurmukhi":"DONsy vjx lgy","unicode":"ਧੌਂਸੇ ਵਜਣ ਲਗੇ"}},"es":{"sn":""},"hi":{}},"transliteration":{"english":"dhu(n)dhabh baaje ||","hindi":"दुँदभ बाजे ॥","en":"dhu(n)dhabh baaje ||","hi":"दुँदभ बाजे ॥","ipa":"d̪ʊŋd̪əɓ bɑd͡ʒe.","ur":"دُںدبھ باجے ۔۔"},"pageNo":103,"lineNo":79119,"updated":"2022-12-24 02:22:37","visraam":{"sttm2":[],"sttm":[],"igurbani":[]},"writer":{"writerId":47,"gurmukhi":"gurU goibMd isMG jI","unicode":null,"english":"Guru Gobind Singh Ji"},"raag":{"raagId":52,"gurmukhi":null,"unicode":null,"english":null,"raagWithPage":null}},{"verseId":79120,"shabadId":7684,"verse":{"gurmukhi":"sB sur gwjy ]","unicode":"ਸਭ ਸੁਰ ਗਾਜੇ ॥"},"larivaar":{"gurmukhi":"sBsurgwjy]","unicode":"ਸਭਸੁਰਗਾਜੇ॥"},"translation":{"en":{"bdb":"The trumpents sounded and all the gods shouted."},"pu":{"ss":{"gurmukhi":"Aqy swry dyvqy gjx lgy।","unicode":"ਅਤੇ ਸਾਰੇ ਦੇਵਤੇ ਗਜਣ ਲਗੇ।"},"ft":{"gurmukhi":"","unicode":""},"bdb":{"gurmukhi":"Aqy swry dyvqy gjx lgy।","unicode":"ਅਤੇ ਸਾਰੇ ਦੇਵਤੇ ਗਜਣ ਲਗੇ।"}},"es":{"sn":""},"hi":{}},"transliteration":{"english":"sabh sur gaaje ||","hindi":"सभ सुर गाजे ॥","en":"sabh sur gaaje ||","hi":"सभ सुर गाजे ॥","ipa":"səɓ sʊr Gɑd͡ʒe.","ur":"سبھ سُر گاجے ۔۔"},"pageNo":103,"lineNo":79120,"updated":"2022-12-24 02:22:37","visraam":{"sttm2":[],"sttm":[],"igurbani":[]},"writer":{"writerId":47,"gurmukhi":"gurU goibMd isMG jI","unicode":null,"english":"Guru Gobind Singh Ji"},"raag":{"raagId":52,"gurmukhi":null,"unicode":null,"english":null,"raagWithPage":null}},{"verseId":79121,"shabadId":7684,"verse":{"gurmukhi":"krq bfweI ]","unicode":"ਕਰਤ ਬਡਾਈ ॥"},"larivaar":{"gurmukhi":"krqbfweI]","unicode":"ਕਰਤਬਡਾਈ॥"},"translation":{"en":{"bdb":""},"pu":{"ss":{"gurmukhi":"(sB dyvI dI) vifAweI krn lgy","unicode":"(ਸਭ ਦੇਵੀ ਦੀ) ਵਡਿਆਈ ਕਰਨ ਲਗੇ"},"ft":{"gurmukhi":"","unicode":""},"bdb":{"gurmukhi":"(sB dyvI dI) vifAweI krn lgy","unicode":"(ਸਭ ਦੇਵੀ ਦੀ) ਵਡਿਆਈ ਕਰਨ ਲਗੇ"}},"es":{"sn":""},"hi":{}},"transliteration":{"english":"karat baddaiee ||","hindi":"करत बडाई ॥","en":"karat baddaiee ||","hi":"करत बडाई ॥","ipa":"kərət̪ bəɖɑei.","ur":"کرت بڈاای ۔۔"},"pageNo":103,"lineNo":79121,"updated":"2022-12-24 02:22:37","visraam":{"sttm2":[],"sttm":[],"igurbani":[]},"writer":{"writerId":47,"gurmukhi":"gurU goibMd isMG jI","unicode":null,"english":"Guru Gobind Singh Ji"},"raag":{"raagId":52,"gurmukhi":null,"unicode":null,"english":null,"raagWithPage":null}},{"verseId":79122,"shabadId":7684,"verse":{"gurmukhi":"sumn bRKweI ]2]40]","unicode":"ਸੁਮਨ ਬ੍ਰਖਾਈ ॥੨॥੪੦॥"},"larivaar":{"gurmukhi":"sumnbRKweI]2]40]","unicode":"ਸੁਮਨਬ੍ਰਖਾਈ॥੨॥੪੦॥"},"translation":{"en":{"bdb":"They eulogise the godess and shower flowers on her. 2.40."},"pu":{"ss":{"gurmukhi":"(Aqy dyvI auqy) Pulw dI brKw krn l`gy ]2]40]","unicode":"(ਅਤੇ ਦੇਵੀ ਉਤੇ) ਫੁਲਾ ਦੀ ਬਰਖਾ ਕਰਨ ਲੱਗੇ ॥੨॥੪੦॥"},"ft":{"gurmukhi":"","unicode":""},"bdb":{"gurmukhi":"(Aqy dyvI auqy) Pulw dI brKw krn l`gy ]2]40]","unicode":"(ਅਤੇ ਦੇਵੀ ਉਤੇ) ਫੁਲਾ ਦੀ ਬਰਖਾ ਕਰਨ ਲੱਗੇ ॥੨॥੪੦॥"}},"es":{"sn":""},"hi":{}},"transliteration":{"english":"suman brakhaiee ||2||40||","hindi":"सुमन ब्रखाई ॥२॥४०॥","en":"suman brakhaiee ||2||40||","hi":"सुमन ब्रखाई ॥२॥४०॥","ipa":"sʊmən bɹəkʰɑei.2.4ə0.","ur":"سُمن برکھاای ۔۔۲۔۔۴۰۔۔"},"pageNo":103,"lineNo":79122,"updated":"2022-12-24 02:22:37","visraam":{"sttm2":[],"sttm":[],"igurbani":[]},"writer":{"writerId":47,"gurmukhi":"gurU goibMd isMG jI","unicode":null,"english":"Guru Gobind Singh Ji"},"raag":{"raagId":52,"gurmukhi":null,"unicode":null,"english":null,"raagWithPage":null}},{"verseId":79123,"shabadId":7684,"verse":{"gurmukhi":"kInI bhu Arcw ]","unicode":"ਕੀਨੀ ਬਹੁ ਅਰਚਾ ॥"},"larivaar":{"gurmukhi":"kInIbhuArcw]","unicode":"ਕੀਨੀਬਹੁਅਰਚਾ॥"},"translation":{"en":{"bdb":""},"pu":{"ss":{"gurmukhi":"(aunHw ny dyvI dI) bhuq pUjw kIqI","unicode":"(ਉਨ੍ਹਾ ਨੇ ਦੇਵੀ ਦੀ) ਬਹੁਤ ਪੂਜਾ ਕੀਤੀ"},"ft":{"gurmukhi":"","unicode":""},"bdb":{"gurmukhi":"(aunHw ny dyvI dI) bhuq pUjw kIqI","unicode":"(ਉਨ੍ਹਾ ਨੇ ਦੇਵੀ ਦੀ) ਬਹੁਤ ਪੂਜਾ ਕੀਤੀ"}},"es":{"sn":""},"hi":{}},"transliteration":{"english":"keenee bahu arachaa ||","hindi":"कीनी बहु अरचा ॥","en":"keenee bahu arachaa ||","hi":"कीनी बहु अरचा ॥","ipa":"kini bəh ərət͡ʃɑ.","ur":"کیٍنیِ بهُ ارچا ۔۔"},"pageNo":103,"lineNo":79123,"updated":"2022-12-24 02:22:37","visraam":{"sttm2":[],"sttm":[],"igurbani":[]},"writer":{"writerId":47,"gurmukhi":"gurU goibMd isMG jI","unicode":null,"english":"Guru Gobind Singh Ji"},"raag":{"raagId":52,"gurmukhi":null,"unicode":null,"english":null,"raagWithPage":null}},{"verseId":79124,"shabadId":7684,"verse":{"gurmukhi":"js Duin crcw ]","unicode":"ਜਸ ਧੁਨਿ ਚਰਚਾ ॥"},"larivaar":{"gurmukhi":"jsDuincrcw]","unicode":"ਜਸਧੁਨਿਚਰਚਾ॥"},"translation":{"en":{"bdb":"They worshipped the goddess in various ways and sang her poraises."},"pu":{"ss":{"gurmukhi":"Aqy XS-gwn kIqw।","unicode":"ਅਤੇ ਯਸ਼-ਗਾਨ ਕੀਤਾ।"},"ft":{"gurmukhi":"","unicode":""},"bdb":{"gurmukhi":"Aqy XS-gwn kIqw।","unicode":"ਅਤੇ ਯਸ਼-ਗਾਨ ਕੀਤਾ।"}},"es":{"sn":""},"hi":{}},"transliteration":{"english":"jas dhun charachaa ||","hindi":"जस धुनि चरचा ॥","en":"jas dhun charachaa ||","hi":"जस धुनि चरचा ॥","ipa":"d͡ʒəs t̪ʊn t͡ʃərət͡ʃɑ.","ur":"جس دھُن چرچا ۔۔"},"pageNo":103,"lineNo":79124,"updated":"2022-12-24 02:22:37","visraam":{"sttm2":[],"sttm":[],"igurbani":[]},"writer":{"writerId":47,"gurmukhi":"gurU goibMd isMG jI","unicode":null,"english":"Guru Gobind Singh Ji"},"raag":{"raagId":52,"gurmukhi":null,"unicode":null,"english":null,"raagWithPage":null}},{"verseId":79125,"shabadId":7684,"verse":{"gurmukhi":"pwien lwgy ]","unicode":"ਪਾਇਨ ਲਾਗੇ ॥"},"larivaar":{"gurmukhi":"pwienlwgy]","unicode":"ਪਾਇਨਲਾਗੇ॥"},"translation":{"en":{"bdb":""},"pu":{"ss":{"gurmukhi":"(dyvI dy) pYrIN lgy;","unicode":"(ਦੇਵੀ ਦੇ) ਪੈਰੀਂ ਲਗੇ;"},"ft":{"gurmukhi":"","unicode":""},"bdb":{"gurmukhi":"(dyvI dy) pYrIN lgy;","unicode":"(ਦੇਵੀ ਦੇ) ਪੈਰੀਂ ਲਗੇ;"}},"es":{"sn":""},"hi":{}},"transliteration":{"english":"pain laage ||","hindi":"पाइन लागे ॥","en":"pain laage ||","hi":"पाइन लागे ॥","ipa":"pɑeɪn lɑGe.","ur":"پاان لاگے ۔۔"},"pageNo":103,"lineNo":79125,"updated":"2022-12-24 02:22:37","visraam":{"sttm2":[],"sttm":[],"igurbani":[]},"writer":{"writerId":47,"gurmukhi":"gurU goibMd isMG jI","unicode":null,"english":"Guru Gobind Singh Ji"},"raag":{"raagId":52,"gurmukhi":null,"unicode":null,"english":null,"raagWithPage":null}},{"verseId":79126,"shabadId":7684,"verse":{"gurmukhi":"sB duK Bwgy ]3]41]","unicode":"ਸਭ ਦੁਖ ਭਾਗੇ ॥੩॥੪੧॥"},"larivaar":{"gurmukhi":"sBduKBwgy]3]41]","unicode":"ਸਭਦੁਖਭਾਗੇ॥੩॥੪੧॥"},"translation":{"en":{"bdb":"They have touhed her feet and all their sorrows have ended.3.41."},"pu":{"ss":{"gurmukhi":"(PlsrUp aunHw dy) swry duK dUr ho gey ]3]41]","unicode":"(ਫਲਸਰੂਪ ਉਨ੍ਹਾ ਦੇ) ਸਾਰੇ ਦੁਖ ਦੂਰ ਹੋ ਗਏ ॥੩॥੪੧॥"},"ft":{"gurmukhi":"","unicode":""},"bdb":{"gurmukhi":"(PlsrUp aunHw dy) swry duK dUr ho gey ]3]41]","unicode":"(ਫਲਸਰੂਪ ਉਨ੍ਹਾ ਦੇ) ਸਾਰੇ ਦੁਖ ਦੂਰ ਹੋ ਗਏ ॥੩॥੪੧॥"}},"es":{"sn":""},"hi":{}},"transliteration":{"english":"sabh dhukh bhaage ||3||41||","hindi":"सभ दुख भागे ॥३॥४१॥","en":"sabh dhukh bhaage ||3||41||","hi":"सभ दुख भागे ॥३॥४१॥","ipa":"səɓ d̪ʊkʰ ɓɑGe.3.4ə1.","ur":"سبھ دُکھ بھاگے ۔۔۳۔۔۴۱۔۔"},"pageNo":103,"lineNo":79126,"updated":"2022-12-24 02:22:37","visraam":{"sttm2":[],"sttm":[],"igurbani":[]},"writer":{"writerId":47,"gurmukhi":"gurU goibMd isMG jI","unicode":null,"english":"Guru Gobind Singh Ji"},"raag":{"raagId":52,"gurmukhi":null,"unicode":null,"english":null,"raagWithPage":null}},{"verseId":79127,"shabadId":7684,"verse":{"gurmukhi":"gwey jY krKw ]","unicode":"ਗਾਏ ਜੈ ਕਰਖਾ ॥"},"larivaar":{"gurmukhi":"gweyjYkrKw]","unicode":"ਗਾਏਜੈਕਰਖਾ॥"},"translation":{"en":{"bdb":""},"pu":{"ss":{"gurmukhi":"ijq dy CMd (krKw) gwaux lgy","unicode":"ਜਿਤ ਦੇ ਛੰਦ (ਕਰਖਾ) ਗਾਉਣ ਲਗੇ"},"ft":{"gurmukhi":"","unicode":""},"bdb":{"gurmukhi":"ijq dy CMd (krKw) gwaux lgy","unicode":"ਜਿਤ ਦੇ ਛੰਦ (ਕਰਖਾ) ਗਾਉਣ ਲਗੇ"}},"es":{"sn":""},"hi":{}},"transliteration":{"english":"gaae jai karakhaa ||","hindi":"गाए जै करखा ॥","en":"gaae jai karakhaa ||","hi":"गाए जै करखा ॥","ipa":"Gɑee d͡ʒæ kərəkʰɑ.","ur":"گااے جَے کرکھا ۔۔"},"pageNo":103,"lineNo":79127,"updated":"2022-12-24 02:22:37","visraam":{"sttm2":[],"sttm":[],"igurbani":[]},"writer":{"writerId":47,"gurmukhi":"gurU goibMd isMG jI","unicode":null,"english":"Guru Gobind Singh Ji"},"raag":{"raagId":52,"gurmukhi":null,"unicode":null,"english":null,"raagWithPage":null}},{"verseId":79128,"shabadId":7684,"verse":{"gurmukhi":"puhpin brKw ]","unicode":"ਪੁਹਪਨਿ ਬਰਖਾ ॥"},"larivaar":{"gurmukhi":"puhpinbrKw]","unicode":"ਪੁਹਪਨਿਬਰਖਾ॥"},"translation":{"en":{"bdb":"They sang the songs of victory and showered flowers."},"pu":{"ss":{"gurmukhi":"Aqy Pulw dI brKw krn lgy।","unicode":"ਅਤੇ ਫੁਲਾ ਦੀ ਬਰਖਾ ਕਰਨ ਲਗੇ।"},"ft":{"gurmukhi":"","unicode":""},"bdb":{"gurmukhi":"Aqy Pulw dI brKw krn lgy।","unicode":"ਅਤੇ ਫੁਲਾ ਦੀ ਬਰਖਾ ਕਰਨ ਲਗੇ।"}},"es":{"sn":""},"hi":{}},"transliteration":{"english":"puhapan barakhaa ||","hindi":"पुहपनि बरखा ॥","en":"puhapan barakhaa ||","hi":"पुहपनि बरखा ॥","ipa":"pʊhəpən bərəkʰɑ.","ur":"پُهپن برکھا ۔۔"},"pageNo":103,"lineNo":79128,"updated":"2022-12-24 02:22:37","visraam":{"sttm2":[],"sttm":[],"igurbani":[]},"writer":{"writerId":47,"gurmukhi":"gurU goibMd isMG jI","unicode":null,"english":"Guru Gobind Singh Ji"},"raag":{"raagId":52,"gurmukhi":null,"unicode":null,"english":null,"raagWithPage":null}},{"verseId":79129,"shabadId":7684,"verse":{"gurmukhi":"sIs invwey ]","unicode":"ਸੀਸ ਨਿਵਾਏ ॥"},"larivaar":{"gurmukhi":"sIsinvwey]","unicode":"ਸੀਸਨਿਵਾਏ॥"},"translation":{"en":{"bdb":""},"pu":{"ss":{"gurmukhi":"(aunHw ny dyvI Agy) sIs Jukwey","unicode":"(ਉਨ੍ਹਾ ਨੇ ਦੇਵੀ ਅਗੇ) ਸੀਸ ਝੁਕਾਏ"},"ft":{"gurmukhi":"","unicode":""},"bdb":{"gurmukhi":"(aunHw ny dyvI Agy) sIs Jukwey","unicode":"(ਉਨ੍ਹਾ ਨੇ ਦੇਵੀ ਅਗੇ) ਸੀਸ ਝੁਕਾਏ"}},"es":{"sn":""},"hi":{}},"transliteration":{"english":"sees nivaae ||","hindi":"सीस निवाए ॥","en":"sees nivaae ||","hi":"सीस निवाए ॥","ipa":"sis nɪʋɑee.","ur":"سیِس نوااے ۔۔"},"pageNo":103,"lineNo":79129,"updated":"2022-12-24 02:22:37","visraam":{"sttm2":[],"sttm":[],"igurbani":[]},"writer":{"writerId":47,"gurmukhi":"gurU goibMd isMG jI","unicode":null,"english":"Guru Gobind Singh Ji"},"raag":{"raagId":52,"gurmukhi":null,"unicode":null,"english":null,"raagWithPage":null}},{"verseId":79130,"shabadId":7684,"verse":{"gurmukhi":"sB suK pwey ]4]42]","unicode":"ਸਭ ਸੁਖ ਪਾਏ ॥੪॥੪੨॥"},"larivaar":{"gurmukhi":"sBsuKpwey]4]42]","unicode":"ਸਭਸੁਖਪਾਏ॥੪॥੪੨॥"},"translation":{"en":{"bdb":"They bowed their heads and obtained great comfort.4.42."},"pu":{"ss":{"gurmukhi":"(Aqy Aijhw krky) sB qrHw dy suK pRwpq kIqy ]4]42]","unicode":"(ਅਤੇ ਅਜਿਹਾ ਕਰਕੇ) ਸਭ ਤਰ੍ਹਾ ਦੇ ਸੁਖ ਪ੍ਰਾਪਤ ਕੀਤੇ ॥੪॥੪੨॥"},"ft":{"gurmukhi":"","unicode":""},"bdb":{"gurmukhi":"(Aqy Aijhw krky) sB qrHw dy suK pRwpq kIqy ]4]42]","unicode":"(ਅਤੇ ਅਜਿਹਾ ਕਰਕੇ) ਸਭ ਤਰ੍ਹਾ ਦੇ ਸੁਖ ਪ੍ਰਾਪਤ ਕੀਤੇ ॥੪॥੪੨॥"}},"es":{"sn":""},"hi":{}},"transliteration":{"english":"sabh sukh paae ||4||42||","hindi":"सभ सुख पाए ॥४॥४२॥","en":"sabh sukh paae ||4||42||","hi":"सभ सुख पाए ॥४॥४२॥","ipa":"səɓ sʊkʰ pɑee.4.4ə2.","ur":"سبھ سُکھ پااے ۔۔۴۔۔۴۲۔۔"},"pageNo":103,"lineNo":79130,"updated":"2022-12-24 02:22:37","visraam":{"sttm2":[],"sttm":[],"igurbani":[]},"writer":{"writerId":47,"gurmukhi":"gurU goibMd isMG jI","unicode":null,"english":"Guru Gobind Singh Ji"},"raag":{"raagId":52,"gurmukhi":null,"unicode":null,"english":null,"raagWithPage":null}},{"verseId":79131,"shabadId":7685,"verse":{"gurmukhi":"dohrw ]","unicode":"ਦੋਹਰਾ ॥"},"larivaar":{"gurmukhi":"dohrw]","unicode":"ਦੋਹਰਾ॥"},"translation":{"en":{"bdb":"DOHRA"},"pu":{"ss":{"gurmukhi":"dohrw:","unicode":"ਦੋਹਰਾ:"},"ft":{"gurmukhi":"","unicode":""},"bdb":{"gurmukhi":"dohrw:","unicode":"ਦੋਹਰਾ:"}},"es":{"sn":""},"hi":{}},"transliteration":{"english":"dhoharaa ||","hindi":"दोहरा ॥","en":"dhoharaa ||","hi":"दोहरा ॥","ipa":"d̪ɔhərɑ.","ur":"دوهرا ۔۔"},"pageNo":103,"lineNo":79131,"updated":"2022-12-24 02:22:37","visraam":{"sttm":[],"igurbani":[],"sttm2":[]},"writer":{"writerId":47,"gurmukhi":"gurU goibMd isMG jI","unicode":null,"english":"Guru Gobind Singh Ji"},"raag":{"raagId":52,"gurmukhi":null,"unicode":null,"english":null,"raagWithPage":null}},{"verseId":79132,"shabadId":7685,"verse":{"gurmukhi":"lop cMifkw jU BeI dY dyvn ko rwju ]","unicode":"ਲੋਪ ਚੰਡਿਕਾ ਜੂ ਭਈ ਦੈ ਦੇਵਨ ਕੋ ਰਾਜੁ ॥"},"larivaar":{"gurmukhi":"lopcMifkwjUBeIdYdyvnkorwju]","unicode":"ਲੋਪਚੰਡਿਕਾਜੂਭਈਦੈਦੇਵਨਕੋਰਾਜੁ॥"},"translation":{"en":{"bdb":"The goddess Chandi disappeared after bestowing kingdom on the gods."},"pu":{"ss":{"gurmukhi":"dyviqAW nUM rwj dy ky cMifkw jI lop ho geI।","unicode":"ਦੇਵਤਿਆਂ ਨੂੰ ਰਾਜ ਦੇ ਕੇ ਚੰਡਿਕਾ ਜੀ ਲੋਪ ਹੋ ਗਈ।"},"ft":{"gurmukhi":"","unicode":""},"bdb":{"gurmukhi":"dyviqAW nUM rwj dy ky cMifkw jI lop ho geI।","unicode":"ਦੇਵਤਿਆਂ ਨੂੰ ਰਾਜ ਦੇ ਕੇ ਚੰਡਿਕਾ ਜੀ ਲੋਪ ਹੋ ਗਈ।"}},"es":{"sn":""},"hi":{}},"transliteration":{"english":"lop cha(n)ddikaa joo bhiee dhai dhevan ko raaj ||","hindi":"लोप चंडिका जू भई दै देवन को राजु ॥","en":"lop cha(n)ddikaa joo bhiee dhai dhevan ko raaj ||","hi":"लोप चंडिका जू भई दै देवन को राजु ॥","ipa":"lɔp t͡ʃəŋɖɪkɑ d͡ʒu ɓei d̪æ d̪eʋən kɔ rɑd͡ʒ.","ur":"لوپ چںڈکا جُو بھای دَے دےون کو راج ۔۔"},"pageNo":103,"lineNo":79132,"updated":"2022-12-24 02:22:37","visraam":{"sttm2":[],"sttm":[],"igurbani":[]},"writer":{"writerId":47,"gurmukhi":"gurU goibMd isMG jI","unicode":null,"english":"Guru Gobind Singh Ji"},"raag":{"raagId":52,"gurmukhi":null,"unicode":null,"english":null,"raagWithPage":null}},{"verseId":79133,"shabadId":7685,"verse":{"gurmukhi":"bhur suMB nYsuMB duAY dYq bVy isrqwj ]5]43]","unicode":"ਬਹੁਰ ਸੁੰਭ ਨੈਸੁੰਭ ਦੁਐ ਦੈਤ ਬੜੇ ਸਿਰਤਾਜ ॥੫॥੪੩॥"},"larivaar":{"gurmukhi":"bhursuMBnYsuMBduAYdYqbVyisrqwj]5]43]","unicode":"ਬਹੁਰਸੁੰਭਨੈਸੁੰਭਦੁਐਦੈਤਬੜੇਸਿਰਤਾਜ॥੫॥੪੩॥"},"translation":{"en":{"bdb":"Then after some time, both the demons kings came to power.5.43."},"pu":{"ss":{"gurmukhi":"iPr SuMB-inSuMB nw dy do dYNq iSromxI (bx ky) zor pkV gey ]5]43]","unicode":"ਫਿਰ ਸ਼ੁੰਭ-ਨਿਸ਼ੁੰਭ ਨਾ ਦੇ ਦੋ ਦੈਂਤ ਸ਼ਿਰੋਮਣੀ (ਬਣ ਕੇ) ਜ਼ੋਰ ਪਕੜ ਗਏ ॥੫॥੪੩॥"},"ft":{"gurmukhi":"","unicode":""},"bdb":{"gurmukhi":"iPr SuMB-inSuMB nw dy do dYNq iSromxI (bx ky) zor pkV gey ]5]43]","unicode":"ਫਿਰ ਸ਼ੁੰਭ-ਨਿਸ਼ੁੰਭ ਨਾ ਦੇ ਦੋ ਦੈਂਤ ਸ਼ਿਰੋਮਣੀ (ਬਣ ਕੇ) ਜ਼ੋਰ ਪਕੜ ਗਏ ॥੫॥੪੩॥"}},"es":{"sn":""},"hi":{}},"transliteration":{"english":"bahur su(n)bh naisu(n)bh dhuaai dhait baRe sirataaj ||5||43||","hindi":"बहुर सुँभ नैसुँभ दुऐ दैत बड़े सिरताज ॥५॥४३॥","en":"bahur su(n)bh naisu(n)bh dhuaai dhait baRe sirataaj ||5||43||","hi":"बहुर सुँभ नैसुँभ दुऐ दैत बड़े सिरताज ॥५॥४३॥","ipa":"bəhʊr sʊŋɓ næsʊŋɓ d̪ʊæ d̪æt̪ bəɽe sɪrət̪ɑd͡ʒ.5.4ə3.","ur":"بهُر سُںبھ نَےسںبھ دُاَے دَےت بڑے سرتاج ۔۔۵۔۔۴۳۔۔"},"pageNo":103,"lineNo":79133,"updated":"2022-12-24 02:22:37","visraam":{"sttm2":[],"sttm":[],"igurbani":[]},"writer":{"writerId":47,"gurmukhi":"gurU goibMd isMG jI","unicode":null,"english":"Guru Gobind Singh Ji"},"raag":{"raagId":52,"gurmukhi":null,"unicode":null,"english":null,"raagWithPage":null}},{"verseId":79134,"shabadId":7686,"verse":{"gurmukhi":"cOpeI ]","unicode":"ਚੌਪਈ ॥"},"larivaar":{"gurmukhi":"cOpeI]","unicode":"ਚੌਪਈ॥"},"translation":{"en":{"bdb":"CHAUPAI"},"pu":{"ss":{"gurmukhi":"cOpeI:","unicode":"ਚੌਪਈ:"},"ft":{"gurmukhi":"","unicode":""},"bdb":{"gurmukhi":"cOpeI:","unicode":"ਚੌਪਈ:"}},"es":{"sn":""},"hi":{}},"transliteration":{"english":"chauapiee ||","hindi":"चौपई ॥","en":"chauapiee ||","hi":"चौपई ॥","ipa":"t͡ʃɒəpei.","ur":"چَوپای ۔۔"},"pageNo":103,"lineNo":79134,"updated":"2022-12-24 02:22:37","visraam":{"sttm":[],"igurbani":[],"sttm2":[]},"writer":{"writerId":47,"gurmukhi":"gurU goibMd isMG jI","unicode":null,"english":"Guru Gobind Singh Ji"},"raag":{"raagId":52,"gurmukhi":null,"unicode":null,"english":null,"raagWithPage":null}},{"verseId":79135,"shabadId":7686,"verse":{"gurmukhi":"suMB insuMB cVy lY kY dl ]","unicode":"ਸੁੰਭ ਨਿਸੁੰਭ ਚੜੇ ਲੈ ਕੈ ਦਲ ॥"},"larivaar":{"gurmukhi":"suMBinsuMBcVylYkYdl]","unicode":"ਸੁੰਭਨਿਸੁੰਭਚੜੇਲੈਕੈਦਲ॥"},"translation":{"en":{"bdb":"Both Sumbh and Nisumbh marched with their forces."},"pu":{"ss":{"gurmukhi":"SuMB Aqy inSuMB &Oj lY ky cVH pey","unicode":"ਸ਼ੁੰਭ ਅਤੇ ਨਿਸ਼ੁੰਭ ਫ਼ੌਜ ਲੈ ਕੇ ਚੜ੍ਹ ਪਏ"},"ft":{"gurmukhi":"","unicode":""},"bdb":{"gurmukhi":"SuMB Aqy inSuMB &Oj lY ky cVH pey","unicode":"ਸ਼ੁੰਭ ਅਤੇ ਨਿਸ਼ੁੰਭ ਫ਼ੌਜ ਲੈ ਕੇ ਚੜ੍ਹ ਪਏ"}},"es":{"sn":""},"hi":{}},"transliteration":{"english":"su(n)bh nisu(n)bh chaRe lai kai dhal ||","hindi":"सुँभ निसुँभ चड़े लै कै दल ॥","en":"su(n)bh nisu(n)bh chaRe lai kai dhal ||","hi":"सुँभ निसुँभ चड़े लै कै दल ॥","ipa":"sʊŋɓ nɪsʊŋɓ t͡ʃəɽe læ kæ d̪əl.","ur":"سُںبھ نسںبھ چڑے لَے کَے دل ۔۔"},"pageNo":103,"lineNo":79135,"updated":"2022-12-24 02:22:37","visraam":{"sttm":[],"igurbani":[],"sttm2":[]},"writer":{"writerId":47,"gurmukhi":"gurU goibMd isMG jI","unicode":null,"english":"Guru Gobind Singh Ji"},"raag":{"raagId":52,"gurmukhi":null,"unicode":null,"english":null,"raagWithPage":null}},{"verseId":79136,"shabadId":7686,"verse":{"gurmukhi":"Air Anyk jIqy ijn jil Qil ]","unicode":"ਅਰਿ ਅਨੇਕ ਜੀਤੇ ਜਿਨ ਜਲਿ ਥਲਿ ॥"},"larivaar":{"gurmukhi":"AirAnykjIqyijnjilQil]","unicode":"ਅਰਿਅਨੇਕਜੀਤੇਜਿਨਜਲਿਥਲਿ॥"},"translation":{"en":{"bdb":"They conquered many enemies in water and on land."},"pu":{"ss":{"gurmukhi":"ijnHw ny jl Aqy Ql dy Anykw vYrIAW nUM ijq ilAw।","unicode":"ਜਿਨ੍ਹਾ ਨੇ ਜਲ ਅਤੇ ਥਲ ਦੇ ਅਨੇਕਾ ਵੈਰੀਆਂ ਨੂੰ ਜਿਤ ਲਿਆ।"},"ft":{"gurmukhi":"","unicode":""},"bdb":{"gurmukhi":"ijnHw ny jl Aqy Ql dy Anykw vYrIAW nUM ijq ilAw।","unicode":"ਜਿਨ੍ਹਾ ਨੇ ਜਲ ਅਤੇ ਥਲ ਦੇ ਅਨੇਕਾ ਵੈਰੀਆਂ ਨੂੰ ਜਿਤ ਲਿਆ।"}},"es":{"sn":""},"hi":{}},"transliteration":{"english":"ar anek jeete jin jal thal ||","hindi":"अरि अनेक जीते जिन जलि थलि ॥","en":"ar anek jeete jin jal thal ||","hi":"अरि अनेक जीते जिन जलि थलि ॥","ipa":"ər ənek d͡ʒit̪e d͡ʒɪn d͡ʒəl t̪ʰəl.","ur":"ار انےک جیِتے جن جلِ تھلِ ۔۔"},"pageNo":103,"lineNo":79136,"updated":"2022-12-24 02:22:37","visraam":{"sttm2":[],"sttm":[],"igurbani":[]},"writer":{"writerId":47,"gurmukhi":"gurU goibMd isMG jI","unicode":null,"english":"Guru Gobind Singh Ji"},"raag":{"raagId":52,"gurmukhi":null,"unicode":null,"english":null,"raagWithPage":null}},{"verseId":79137,"shabadId":7686,"verse":{"gurmukhi":"dyv rwj ko rwj iCnwvw ]","unicode":"ਦੇਵ ਰਾਜ ਕੋ ਰਾਜ ਛਿਨਾਵਾ ॥"},"larivaar":{"gurmukhi":"dyvrwjkorwjiCnwvw]","unicode":"ਦੇਵਰਾਜਕੋਰਾਜਛਿਨਾਵਾ॥"},"translation":{"en":{"bdb":"They seized the kingdom of Indra, the king of gods."},"pu":{"ss":{"gurmukhi":"ijnHw ny ieMdr dw rwj Koh ilAw","unicode":"ਜਿਨ੍ਹਾ ਨੇ ਇੰਦਰ ਦਾ ਰਾਜ ਖੋਹ ਲਿਆ"},"ft":{"gurmukhi":"","unicode":""},"bdb":{"gurmukhi":"ijnHw ny ieMdr dw rwj Koh ilAw","unicode":"ਜਿਨ੍ਹਾ ਨੇ ਇੰਦਰ ਦਾ ਰਾਜ ਖੋਹ ਲਿਆ"}},"es":{"sn":""},"hi":{}},"transliteration":{"english":"dhev raaj ko raaj chhinaavaa ||","hindi":"देव राज को राज छिनावा ॥","en":"dhev raaj ko raaj chhinaavaa ||","hi":"देव राज को राज छिनावा ॥","ipa":"d̪eʋ rɑd͡ʒ kɔ rɑd͡ʒ ɕɪnɑʋɑ.","ur":"دےو راج کو راج چھناوا ۔۔"},"pageNo":103,"lineNo":79137,"updated":"2022-12-24 02:22:37","visraam":{"sttm2":[],"sttm":[],"igurbani":[]},"writer":{"writerId":47,"gurmukhi":"gurU goibMd isMG jI","unicode":null,"english":"Guru Gobind Singh Ji"},"raag":{"raagId":52,"gurmukhi":null,"unicode":null,"english":null,"raagWithPage":null}},{"verseId":79138,"shabadId":7686,"verse":{"gurmukhi":"syis mukt min Byt pTwvw ]6]44]","unicode":"ਸੇਸਿ ਮੁਕਟ ਮਨਿ ਭੇਟ ਪਠਾਵਾ ॥੬॥੪੪॥"},"larivaar":{"gurmukhi":"syismuktminBytpTwvw]6]44]","unicode":"ਸੇਸਿਮੁਕਟਮਨਿਭੇਟਪਠਾਵਾ॥੬॥੪੪॥"},"translation":{"en":{"bdb":"Sheshanaga sent his head-jewel as a gift.6.44."},"pu":{"ss":{"gurmukhi":"(Aqy ijnHw nUM) SySnwg ny isr dI mxI Bytw vjoN ByjI ]6]44]","unicode":"(ਅਤੇ ਜਿਨ੍ਹਾ ਨੂੰ) ਸ਼ੇਸ਼ਨਾਗ ਨੇ ਸਿਰ ਦੀ ਮਣੀ ਭੇਟਾ ਵਜੋਂ ਭੇਜੀ ॥੬॥੪੪॥"},"ft":{"gurmukhi":"","unicode":""},"bdb":{"gurmukhi":"(Aqy ijnHw nUM) SySnwg ny isr dI mxI Bytw vjoN ByjI ]6]44]","unicode":"(ਅਤੇ ਜਿਨ੍ਹਾ ਨੂੰ) ਸ਼ੇਸ਼ਨਾਗ ਨੇ ਸਿਰ ਦੀ ਮਣੀ ਭੇਟਾ ਵਜੋਂ ਭੇਜੀ ॥੬॥੪੪॥"}},"es":{"sn":""},"hi":{}},"transliteration":{"english":"ses mukaT man bheT paThaavaa ||6||44||","hindi":"सेसि मुकट मनि भेट पठावा ॥६॥४४॥","en":"ses mukaT man bheT paThaavaa ||6||44||","hi":"सेसि मुकट मनि भेट पठावा ॥६॥४४॥","ipa":"ses mʊkəʈ mən ɓeʈ pəʈʰɑʋɑ.6.4ə4.","ur":"سےس مُکٹ من بھےٹ پٹھاوا ۔۔۶۔۔۴۴۔۔"},"pageNo":103,"lineNo":79138,"updated":"2022-12-24 02:22:37","visraam":{"sttm2":[],"sttm":[],"igurbani":[]},"writer":{"writerId":47,"gurmukhi":"gurU goibMd isMG jI","unicode":null,"english":"Guru Gobind Singh Ji"},"raag":{"raagId":52,"gurmukhi":null,"unicode":null,"english":null,"raagWithPage":null}}]}